{"box_data": [{"position": {"minX": 201.5, "minY": 267.0, "maxX": 609.5, "maxY": 662.5}, "class_id": 14, "box_caption": "E 0.015", "scores": {"class_score": 0.0146331787109375}, "domain": "pixel"}, {"position": {"minX": 201.5, "minY": 267.0, "maxX": 609.5, "maxY": 662.5}, "class_id": 31, "box_caption": "V 0.014", "scores": {"class_score": 0.014251708984375}, "domain": "pixel"}, {"position": {"minX": 197.0, "minY": 267.5, "maxX": 613.5, "maxY": 663.5}, "class_id": 25, "box_caption": "P 0.014", "scores": {"class_score": 0.01383209228515625}, "domain": "pixel"}, {"position": {"minX": 201.5, "minY": 267.0, "maxX": 609.5, "maxY": 662.5}, "class_id": 19, "box_caption": "J 0.014", "scores": {"class_score": 0.013763427734375}, "domain": "pixel"}, {"position": {"minX": 201.5, "minY": 267.0, "maxX": 609.5, "maxY": 662.5}, "class_id": 27, "box_caption": "R 0.014", "scores": {"class_score": 0.01369476318359375}, "domain": "pixel"}, {"position": {"minX": 197.0, "minY": 267.5, "maxX": 613.5, "maxY": 663.5}, "class_id": 10, "box_caption": "A 0.013", "scores": {"class_score": 0.0134429931640625}, "domain": "pixel"}, {"position": {"minX": 201.5, "minY": 267.0, "maxX": 609.5, "maxY": 662.5}, "class_id": 0, "box_caption": "0 0.013", "scores": {"class_score": 0.01340484619140625}, "domain": "pixel"}, {"position": {"minX": 201.5, "minY": 267.0, "maxX": 609.5, "maxY": 662.5}, "class_id": 8, "box_caption": "8 0.013", "scores": {"class_score": 0.0133514404296875}, "domain": "pixel"}, {"position": {"minX": 197.0, "minY": 267.5, "maxX": 613.5, "maxY": 663.5}, "class_id": 35, "box_caption": "Z 0.013", "scores": {"class_score": 0.0128936767578125}, "domain": "pixel"}, {"position": {"minX": 201.5, "minY": 267.0, "maxX": 609.5, "maxY": 662.5}, "class_id": 43, "box_caption": "n 0.013", "scores": {"class_score": 0.01285552978515625}, "domain": "pixel"}, {"position": {"minX": 201.5, "minY": 267.0, "maxX": 609.5, "maxY": 662.5}, "class_id": 17, "box_caption": "H 0.013", "scores": {"class_score": 0.01276397705078125}, "domain": "pixel"}, {"position": {"minX": 197.0, "minY": 267.5, "maxX": 613.5, "maxY": 663.5}, "class_id": 41, "box_caption": "g 0.013", "scores": {"class_score": 0.01274871826171875}, "domain": "pixel"}, {"position": {"minX": 197.0, "minY": 213.25, "maxX": 612.0, "maxY": 660.0}, "class_id": 33, "box_caption": "X 0.013", "scores": {"class_score": 0.01264190673828125}, "domain": "pixel"}, {"position": {"minX": 201.5, "minY": 267.0, "maxX": 609.5, "maxY": 662.5}, "class_id": 16, "box_caption": "G 0.013", "scores": {"class_score": 0.01264190673828125}, "domain": "pixel"}, {"position": {"minX": 201.5, "minY": 267.0, "maxX": 609.5, "maxY": 662.5}, "class_id": 45, "box_caption": "r 0.013", "scores": {"class_score": 0.01264190673828125}, "domain": "pixel"}, {"position": {"minX": 197.0, "minY": 267.5, "maxX": 613.5, "maxY": 663.5}, "class_id": 46, "box_caption": "t 0.013", "scores": {"class_score": 0.0125732421875}, "domain": "pixel"}, {"position": {"minX": 197.0, "minY": 267.5, "maxX": 613.5, "maxY": 663.5}, "class_id": 24, "box_caption": "O 0.013", "scores": {"class_score": 0.01255035400390625}, "domain": "pixel"}, {"position": {"minX": 201.5, "minY": 267.0, "maxX": 609.5, "maxY": 662.5}, "class_id": 6, "box_caption": "6 0.012", "scores": {"class_score": 0.01248931884765625}, "domain": "pixel"}, {"position": {"minX": 201.5, "minY": 267.0, "maxX": 609.5, "maxY": 662.5}, "class_id": 3, "box_caption": "3 0.012", "scores": {"class_score": 0.0123748779296875}, "domain": "pixel"}, {"position": {"minX": 201.5, "minY": 267.0, "maxX": 609.5, "maxY": 662.5}, "class_id": 13, "box_caption": "D 0.012", "scores": {"class_score": 0.0123291015625}, "domain": "pixel"}, {"position": {"minX": 201.5, "minY": 267.0, "maxX": 609.5, "maxY": 662.5}, "class_id": 22, "box_caption": "M 0.012", "scores": {"class_score": 0.01227569580078125}, "domain": "pixel"}, {"position": {"minX": 201.5, "minY": 267.0, "maxX": 609.5, "maxY": 662.5}, "class_id": 21, "box_caption": "L 0.012", "scores": {"class_score": 0.01226043701171875}, "domain": "pixel"}, {"position": {"minX": 197.0, "minY": 267.5, "maxX": 613.5, "maxY": 663.5}, "class_id": 34, "box_caption": "Y 0.012", "scores": {"class_score": 0.012176513671875}, "domain": "pixel"}, {"position": {"minX": 201.5, "minY": 267.0, "maxX": 609.5, "maxY": 662.5}, "class_id": 7, "box_caption": "7 0.012", "scores": {"class_score": 0.01213836669921875}, "domain": "pixel"}, {"position": {"minX": 190.625, "minY": 215.25, "maxX": 617.5, "maxY": 660.0}, "class_id": 36, "box_caption": "a 0.012", "scores": {"class_score": 0.0120849609375}, "domain": "pixel"}, {"position": {"minX": 201.5, "minY": 267.0, "maxX": 609.5, "maxY": 662.5}, "class_id": 26, "box_caption": "Q 0.012", "scores": {"class_score": 0.01204681396484375}, "domain": "pixel"}, {"position": {"minX": 201.5, "minY": 267.0, "maxX": 609.5, "maxY": 662.5}, "class_id": 38, "box_caption": "d 0.012", "scores": {"class_score": 0.01204681396484375}, "domain": "pixel"}, {"position": {"minX": 201.5, "minY": 267.0, "maxX": 609.5, "maxY": 662.5}, "class_id": 11, "box_caption": "B 0.012", "scores": {"class_score": 0.01190948486328125}, "domain": "pixel"}, {"position": {"minX": 197.0, "minY": 267.5, "maxX": 613.5, "maxY": 663.5}, "class_id": 30, "box_caption": "U 0.012", "scores": {"class_score": 0.0118408203125}, "domain": "pixel"}, {"position": {"minX": 197.0, "minY": 267.5, "maxX": 613.5, "maxY": 663.5}, "class_id": 29, "box_caption": "T 0.012", "scores": {"class_score": 0.01178741455078125}, "domain": "pixel"}, {"position": {"minX": 197.0, "minY": 267.5, "maxX": 613.5, "maxY": 663.5}, "class_id": 23, "box_caption": "N 0.012", "scores": {"class_score": 0.0117645263671875}, "domain": "pixel"}, {"position": {"minX": 197.0, "minY": 267.5, "maxX": 613.5, "maxY": 663.5}, "class_id": 5, "box_caption": "5 0.012", "scores": {"class_score": 0.0117034912109375}, "domain": "pixel"}, {"position": {"minX": 197.0, "minY": 267.5, "maxX": 613.5, "maxY": 663.5}, "class_id": 40, "box_caption": "f 0.012", "scores": {"class_score": 0.01168060302734375}, "domain": "pixel"}, {"position": {"minX": 197.0, "minY": 267.5, "maxX": 613.5, "maxY": 663.5}, "class_id": 4, "box_caption": "4 0.012", "scores": {"class_score": 0.01158905029296875}, "domain": "pixel"}, {"position": {"minX": 197.0, "minY": 267.5, "maxX": 613.5, "maxY": 663.5}, "class_id": 44, "box_caption": "q 0.012", "scores": {"class_score": 0.01158905029296875}, "domain": "pixel"}, {"position": {"minX": 197.0, "minY": 267.5, "maxX": 613.5, "maxY": 663.5}, "class_id": 39, "box_caption": "e 0.012", "scores": {"class_score": 0.011505126953125}, "domain": "pixel"}, {"position": {"minX": 197.0, "minY": 267.5, "maxX": 613.5, "maxY": 663.5}, "class_id": 42, "box_caption": "h 0.011", "scores": {"class_score": 0.0114593505859375}, "domain": "pixel"}, {"position": {"minX": 197.0, "minY": 267.5, "maxX": 613.5, "maxY": 663.5}, "class_id": 20, "box_caption": "K 0.011", "scores": {"class_score": 0.01141357421875}, "domain": "pixel"}, {"position": {"minX": 201.5, "minY": 267.0, "maxX": 609.5, "maxY": 662.5}, "class_id": 9, "box_caption": "9 0.011", "scores": {"class_score": 0.01137542724609375}, "domain": "pixel"}, {"position": {"minX": 197.0, "minY": 267.5, "maxX": 613.5, "maxY": 663.5}, "class_id": 37, "box_caption": "b 0.011", "scores": {"class_score": 0.01134490966796875}, "domain": "pixel"}, {"position": {"minX": 197.0, "minY": 267.5, "maxX": 613.5, "maxY": 663.5}, "class_id": 2, "box_caption": "2 0.011", "scores": {"class_score": 0.01126861572265625}, "domain": "pixel"}, {"position": {"minX": 201.5, "minY": 267.0, "maxX": 609.5, "maxY": 662.5}, "class_id": 12, "box_caption": "C 0.011", "scores": {"class_score": 0.0111846923828125}, "domain": "pixel"}, {"position": {"minX": 201.5, "minY": 267.0, "maxX": 609.5, "maxY": 662.5}, "class_id": 1, "box_caption": "1 0.011", "scores": {"class_score": 0.01111602783203125}, "domain": "pixel"}, {"position": {"minX": 299.25, "minY": 333.75, "maxX": 692.0, "maxY": 662.0}, "class_id": 30, "box_caption": "U 0.011", "scores": {"class_score": 0.011016845703125}, "domain": "pixel"}, {"position": {"minX": 299.0, "minY": 335.0, "maxX": 691.0, "maxY": 662.5}, "class_id": 34, "box_caption": "Y 0.011", "scores": {"class_score": 0.01099395751953125}, "domain": "pixel"}, {"position": {"minX": 197.0, "minY": 267.5, "maxX": 613.5, "maxY": 663.5}, "class_id": 18, "box_caption": "I 0.011", "scores": {"class_score": 0.01096343994140625}, "domain": "pixel"}, {"position": {"minX": 299.25, "minY": 333.75, "maxX": 692.0, "maxY": 662.0}, "class_id": 31, "box_caption": "V 0.011", "scores": {"class_score": 0.010955810546875}, "domain": "pixel"}, {"position": {"minX": 197.0, "minY": 267.5, "maxX": 613.5, "maxY": 663.5}, "class_id": 32, "box_caption": "W 0.011", "scores": {"class_score": 0.01094818115234375}, "domain": "pixel"}, {"position": {"minX": 299.0, "minY": 335.0, "maxX": 691.0, "maxY": 662.5}, "class_id": 35, "box_caption": "Z 0.011", "scores": {"class_score": 0.0108489990234375}, "domain": "pixel"}, {"position": {"minX": 299.0, "minY": 335.0, "maxX": 691.0, "maxY": 662.5}, "class_id": 36, "box_caption": "a 0.011", "scores": {"class_score": 0.0107879638671875}, "domain": "pixel"}, {"position": {"minX": 190.625, "minY": 215.25, "maxX": 617.5, "maxY": 660.0}, "class_id": 28, "box_caption": "S 0.011", "scores": {"class_score": 0.0107574462890625}, "domain": "pixel"}, {"position": {"minX": -1.6875, "minY": -1.875, "maxX": 216.5, "maxY": 360.5}, "class_id": 33, "box_caption": "X 0.011", "scores": {"class_score": 0.0106353759765625}, "domain": "pixel"}, {"position": {"minX": -2.375, "minY": -0.625, "maxX": 216.875, "maxY": 358.0}, "class_id": 17, "box_caption": "H 0.011", "scores": {"class_score": 0.01062774658203125}, "domain": "pixel"}, {"position": {"minX": 299.25, "minY": 333.75, "maxX": 692.0, "maxY": 662.0}, "class_id": 14, "box_caption": "E 0.011", "scores": {"class_score": 0.0106048583984375}, "domain": "pixel"}, {"position": {"minX": 299.0, "minY": 335.0, "maxX": 691.0, "maxY": 662.5}, "class_id": 27, "box_caption": "R 0.011", "scores": {"class_score": 0.01059722900390625}, "domain": "pixel"}, {"position": {"minX": 299.25, "minY": 333.75, "maxX": 692.0, "maxY": 662.0}, "class_id": 28, "box_caption": "S 0.011", "scores": {"class_score": 0.01058197021484375}, "domain": "pixel"}, {"position": {"minX": -2.375, "minY": -0.625, "maxX": 216.875, "maxY": 358.0}, "class_id": 0, "box_caption": "0 0.011", "scores": {"class_score": 0.01058197021484375}, "domain": "pixel"}, {"position": {"minX": 299.25, "minY": 333.75, "maxX": 692.0, "maxY": 662.0}, "class_id": 25, "box_caption": "P 0.010", "scores": {"class_score": 0.0104827880859375}, "domain": "pixel"}, {"position": {"minX": 299.25, "minY": 333.75, "maxX": 692.0, "maxY": 662.0}, "class_id": 8, "box_caption": "8 0.010", "scores": {"class_score": 0.01044464111328125}, "domain": "pixel"}, {"position": {"minX": 299.0, "minY": 335.0, "maxX": 691.0, "maxY": 662.5}, "class_id": 0, "box_caption": "0 0.010", "scores": {"class_score": 0.01038360595703125}, "domain": "pixel"}, {"position": {"minX": 299.0, "minY": 335.0, "maxX": 691.0, "maxY": 662.5}, "class_id": 11, "box_caption": "B 0.010", "scores": {"class_score": 0.01036834716796875}, "domain": "pixel"}, {"position": {"minX": 197.0, "minY": 267.5, "maxX": 613.5, "maxY": 663.5}, "class_id": 15, "box_caption": "F 0.010", "scores": {"class_score": 0.01035308837890625}, "domain": "pixel"}, {"position": {"minX": -1.6875, "minY": -1.875, "maxX": 216.5, "maxY": 360.5}, "class_id": 39, "box_caption": "e 0.010", "scores": {"class_score": 0.0103302001953125}, "domain": "pixel"}, {"position": {"minX": -2.375, "minY": -0.625, "maxX": 216.875, "maxY": 358.0}, "class_id": 6, "box_caption": "6 0.010", "scores": {"class_score": 0.01030731201171875}, "domain": "pixel"}, {"position": {"minX": -1.6875, "minY": -1.875, "maxX": 216.5, "maxY": 360.5}, "class_id": 34, "box_caption": "Y 0.010", "scores": {"class_score": 0.010284423828125}, "domain": "pixel"}, {"position": {"minX": 299.0, "minY": 335.0, "maxX": 691.0, "maxY": 662.5}, "class_id": 12, "box_caption": "C 0.010", "scores": {"class_score": 0.010284423828125}, "domain": "pixel"}, {"position": {"minX": -2.375, "minY": -0.625, "maxX": 216.875, "maxY": 358.0}, "class_id": 25, "box_caption": "P 0.010", "scores": {"class_score": 0.0102691650390625}, "domain": "pixel"}, {"position": {"minX": 299.25, "minY": 333.75, "maxX": 692.0, "maxY": 662.0}, "class_id": 16, "box_caption": "G 0.010", "scores": {"class_score": 0.01023101806640625}, "domain": "pixel"}, {"position": {"minX": -2.375, "minY": -0.625, "maxX": 216.875, "maxY": 358.0}, "class_id": 22, "box_caption": "M 0.010", "scores": {"class_score": 0.0102081298828125}, "domain": "pixel"}, {"position": {"minX": 299.0, "minY": 335.0, "maxX": 691.0, "maxY": 662.5}, "class_id": 19, "box_caption": "J 0.010", "scores": {"class_score": 0.01020050048828125}, "domain": "pixel"}, {"position": {"minX": -1.6875, "minY": -1.875, "maxX": 216.5, "maxY": 360.5}, "class_id": 13, "box_caption": "D 0.010", "scores": {"class_score": 0.01019287109375}, "domain": "pixel"}, {"position": {"minX": 299.0, "minY": 335.0, "maxX": 691.0, "maxY": 662.5}, "class_id": 6, "box_caption": "6 0.010", "scores": {"class_score": 0.01018524169921875}, "domain": "pixel"}, {"position": {"minX": 299.25, "minY": 333.75, "maxX": 692.0, "maxY": 662.0}, "class_id": 37, "box_caption": "b 0.010", "scores": {"class_score": 0.0101470947265625}, "domain": "pixel"}, {"position": {"minX": -2.375, "minY": -0.625, "maxX": 216.875, "maxY": 358.0}, "class_id": 14, "box_caption": "E 0.010", "scores": {"class_score": 0.0101470947265625}, "domain": "pixel"}, {"position": {"minX": 299.25, "minY": 333.75, "maxX": 692.0, "maxY": 662.0}, "class_id": 24, "box_caption": "O 0.010", "scores": {"class_score": 0.0101318359375}, "domain": "pixel"}, {"position": {"minX": -2.375, "minY": -0.625, "maxX": 216.875, "maxY": 358.0}, "class_id": 16, "box_caption": "G 0.010", "scores": {"class_score": 0.0101318359375}, "domain": "pixel"}, {"position": {"minX": 299.25, "minY": 333.75, "maxX": 692.0, "maxY": 662.0}, "class_id": 4, "box_caption": "4 0.010", "scores": {"class_score": 0.01009368896484375}, "domain": "pixel"}, {"position": {"minX": 299.25, "minY": 333.75, "maxX": 692.0, "maxY": 662.0}, "class_id": 39, "box_caption": "e 0.010", "scores": {"class_score": 0.0100555419921875}, "domain": "pixel"}, {"position": {"minX": 299.0, "minY": 335.0, "maxX": 691.0, "maxY": 662.5}, "class_id": 26, "box_caption": "Q 0.010", "scores": {"class_score": 0.01004791259765625}, "domain": "pixel"}, {"position": {"minX": -2.375, "minY": -0.625, "maxX": 216.875, "maxY": 358.0}, "class_id": 26, "box_caption": "Q 0.010", "scores": {"class_score": 0.010040283203125}, "domain": "pixel"}, {"position": {"minX": 299.0, "minY": 335.0, "maxX": 691.0, "maxY": 662.5}, "class_id": 46, "box_caption": "t 0.010", "scores": {"class_score": 0.01003265380859375}, "domain": "pixel"}, {"position": {"minX": 139.5, "minY": 115.25, "maxX": 534.0, "maxY": 626.0}, "class_id": 0, "box_caption": "0 0.010", "scores": {"class_score": 0.0100250244140625}, "domain": "pixel"}, {"position": {"minX": 142.25, "minY": 117.0, "maxX": 532.0, "maxY": 624.5}, "class_id": 5, "box_caption": "5 0.010", "scores": {"class_score": 0.010009765625}, "domain": "pixel"}, {"position": {"minX": 139.5, "minY": 115.25, "maxX": 534.0, "maxY": 626.0}, "class_id": 27, "box_caption": "R 0.010", "scores": {"class_score": 0.00997161865234375}, "domain": "pixel"}, {"position": {"minX": 299.25, "minY": 333.75, "maxX": 692.0, "maxY": 662.0}, "class_id": 5, "box_caption": "5 0.010", "scores": {"class_score": 0.00994110107421875}, "domain": "pixel"}, {"position": {"minX": -1.6875, "minY": -1.875, "maxX": 216.5, "maxY": 360.5}, "class_id": 20, "box_caption": "K 0.010", "scores": {"class_score": 0.00992584228515625}, "domain": "pixel"}, {"position": {"minX": -1.6875, "minY": -1.875, "maxX": 216.5, "maxY": 360.5}, "class_id": 5, "box_caption": "5 0.010", "scores": {"class_score": 0.0099029541015625}, "domain": "pixel"}, {"position": {"minX": 139.5, "minY": 115.25, "maxX": 534.0, "maxY": 626.0}, "class_id": 13, "box_caption": "D 0.010", "scores": {"class_score": 0.0098724365234375}, "domain": "pixel"}, {"position": {"minX": 139.5, "minY": 115.25, "maxX": 534.0, "maxY": 626.0}, "class_id": 16, "box_caption": "G 0.010", "scores": {"class_score": 0.0098724365234375}, "domain": "pixel"}, {"position": {"minX": -2.375, "minY": -0.625, "maxX": 216.875, "maxY": 358.0}, "class_id": 42, "box_caption": "h 0.010", "scores": {"class_score": 0.00986480712890625}, "domain": "pixel"}, {"position": {"minX": 299.25, "minY": 333.75, "maxX": 692.0, "maxY": 662.0}, "class_id": 33, "box_caption": "X 0.010", "scores": {"class_score": 0.0098419189453125}, "domain": "pixel"}, {"position": {"minX": -2.375, "minY": -0.625, "maxX": 216.875, "maxY": 358.0}, "class_id": 32, "box_caption": "W 0.010", "scores": {"class_score": 0.0098419189453125}, "domain": "pixel"}, {"position": {"minX": -2.375, "minY": -0.625, "maxX": 216.875, "maxY": 358.0}, "class_id": 36, "box_caption": "a 0.010", "scores": {"class_score": 0.0098114013671875}, "domain": "pixel"}, {"position": {"minX": -2.375, "minY": -0.625, "maxX": 216.875, "maxY": 358.0}, "class_id": 37, "box_caption": "b 0.010", "scores": {"class_score": 0.0098114013671875}, "domain": "pixel"}, {"position": {"minX": 299.0, "minY": 335.0, "maxX": 691.0, "maxY": 662.5}, "class_id": 45, "box_caption": "r 0.010", "scores": {"class_score": 0.00980377197265625}, "domain": "pixel"}, {"position": {"minX": -1.6875, "minY": -1.875, "maxX": 216.5, "maxY": 360.5}, "class_id": 27, "box_caption": "R 0.010", "scores": {"class_score": 0.00977325439453125}, "domain": "pixel"}, {"position": {"minX": 299.0, "minY": 335.0, "maxX": 691.0, "maxY": 662.5}, "class_id": 42, "box_caption": "h 0.010", "scores": {"class_score": 0.00977325439453125}, "domain": "pixel"}, {"position": {"minX": -2.375, "minY": -0.625, "maxX": 216.875, "maxY": 358.0}, "class_id": 24, "box_caption": "O 0.010", "scores": {"class_score": 0.0097503662109375}, "domain": "pixel"}, {"position": {"minX": -2.375, "minY": -0.625, "maxX": 216.875, "maxY": 358.0}, "class_id": 46, "box_caption": "t 0.010", "scores": {"class_score": 0.0097503662109375}, "domain": "pixel"}, {"position": {"minX": -1.6875, "minY": -1.875, "maxX": 216.5, "maxY": 360.5}, "class_id": 11, "box_caption": "B 0.010", "scores": {"class_score": 0.009735107421875}, "domain": "pixel"}, {"position": {"minX": 299.0, "minY": 335.0, "maxX": 691.0, "maxY": 662.5}, "class_id": 22, "box_caption": "M 0.010", "scores": {"class_score": 0.00972747802734375}, "domain": "pixel"}, {"position": {"minX": 139.5, "minY": 115.25, "maxX": 534.0, "maxY": 626.0}, "class_id": 26, "box_caption": "Q 0.010", "scores": {"class_score": 0.0097198486328125}, "domain": "pixel"}, {"position": {"minX": 299.25, "minY": 333.75, "maxX": 692.0, "maxY": 662.0}, "class_id": 10, "box_caption": "A 0.010", "scores": {"class_score": 0.00969696044921875}, "domain": "pixel"}, {"position": {"minX": 299.0, "minY": 335.0, "maxX": 691.0, "maxY": 662.5}, "class_id": 3, "box_caption": "3 0.010", "scores": {"class_score": 0.0096893310546875}, "domain": "pixel"}, {"position": {"minX": 299.25, "minY": 333.75, "maxX": 692.0, "maxY": 662.0}, "class_id": 44, "box_caption": "q 0.010", "scores": {"class_score": 0.0096588134765625}, "domain": "pixel"}, {"position": {"minX": -2.375, "minY": -0.625, "maxX": 216.875, "maxY": 358.0}, "class_id": 19, "box_caption": "J 0.010", "scores": {"class_score": 0.0096435546875}, "domain": "pixel"}, {"position": {"minX": 299.25, "minY": 333.75, "maxX": 692.0, "maxY": 662.0}, "class_id": 23, "box_caption": "N 0.010", "scores": {"class_score": 0.00962066650390625}, "domain": "pixel"}, {"position": {"minX": -1.6875, "minY": -1.875, "maxX": 216.5, "maxY": 360.5}, "class_id": 23, "box_caption": "N 0.010", "scores": {"class_score": 0.00960540771484375}, "domain": "pixel"}, {"position": {"minX": -1.6875, "minY": -1.875, "maxX": 216.5, "maxY": 360.5}, "class_id": 9, "box_caption": "9 0.010", "scores": {"class_score": 0.00959014892578125}, "domain": "pixel"}, {"position": {"minX": 299.0, "minY": 335.0, "maxX": 691.0, "maxY": 662.5}, "class_id": 15, "box_caption": "F 0.010", "scores": {"class_score": 0.00958251953125}, "domain": "pixel"}, {"position": {"minX": -1.6875, "minY": -1.875, "maxX": 216.5, "maxY": 360.5}, "class_id": 43, "box_caption": "n 0.010", "scores": {"class_score": 0.00957489013671875}, "domain": "pixel"}, {"position": {"minX": 299.25, "minY": 333.75, "maxX": 692.0, "maxY": 662.0}, "class_id": 41, "box_caption": "g 0.010", "scores": {"class_score": 0.0095672607421875}, "domain": "pixel"}, {"position": {"minX": 299.0, "minY": 335.0, "maxX": 691.0, "maxY": 662.5}, "class_id": 2, "box_caption": "2 0.010", "scores": {"class_score": 0.00955963134765625}, "domain": "pixel"}, {"position": {"minX": 299.0, "minY": 335.0, "maxX": 691.0, "maxY": 662.5}, "class_id": 17, "box_caption": "H 0.010", "scores": {"class_score": 0.00955963134765625}, "domain": "pixel"}, {"position": {"minX": -1.6875, "minY": -1.875, "maxX": 216.5, "maxY": 360.5}, "class_id": 35, "box_caption": "Z 0.010", "scores": {"class_score": 0.009552001953125}, "domain": "pixel"}, {"position": {"minX": 299.0, "minY": 335.0, "maxX": 691.0, "maxY": 662.5}, "class_id": 18, "box_caption": "I 0.010", "scores": {"class_score": 0.00954437255859375}, "domain": "pixel"}, {"position": {"minX": -1.6875, "minY": -1.875, "maxX": 216.5, "maxY": 360.5}, "class_id": 30, "box_caption": "U 0.010", "scores": {"class_score": 0.0095367431640625}, "domain": "pixel"}, {"position": {"minX": 299.25, "minY": 333.75, "maxX": 692.0, "maxY": 662.0}, "class_id": 13, "box_caption": "D 0.009", "scores": {"class_score": 0.00949859619140625}, "domain": "pixel"}, {"position": {"minX": -2.375, "minY": -0.625, "maxX": 216.875, "maxY": 358.0}, "class_id": 40, "box_caption": "f 0.009", "scores": {"class_score": 0.00949859619140625}, "domain": "pixel"}, {"position": {"minX": 139.5, "minY": 115.25, "maxX": 534.0, "maxY": 626.0}, "class_id": 7, "box_caption": "7 0.009", "scores": {"class_score": 0.00949859619140625}, "domain": "pixel"}, {"position": {"minX": 299.0, "minY": 335.0, "maxX": 691.0, "maxY": 662.5}, "class_id": 43, "box_caption": "n 0.009", "scores": {"class_score": 0.009490966796875}, "domain": "pixel"}, {"position": {"minX": -1.6875, "minY": -1.875, "maxX": 216.5, "maxY": 360.5}, "class_id": 3, "box_caption": "3 0.009", "scores": {"class_score": 0.00948333740234375}, "domain": "pixel"}, {"position": {"minX": -2.375, "minY": -0.625, "maxX": 216.875, "maxY": 358.0}, "class_id": 7, "box_caption": "7 0.009", "scores": {"class_score": 0.00946044921875}, "domain": "pixel"}, {"position": {"minX": 139.5, "minY": 115.25, "maxX": 534.0, "maxY": 626.0}, "class_id": 30, "box_caption": "U 0.009", "scores": {"class_score": 0.00946044921875}, "domain": "pixel"}, {"position": {"minX": 139.5, "minY": 115.25, "maxX": 534.0, "maxY": 626.0}, "class_id": 3, "box_caption": "3 0.009", "scores": {"class_score": 0.00945281982421875}, "domain": "pixel"}, {"position": {"minX": -1.6875, "minY": -1.875, "maxX": 216.5, "maxY": 360.5}, "class_id": 2, "box_caption": "2 0.009", "scores": {"class_score": 0.00943756103515625}, "domain": "pixel"}, {"position": {"minX": 139.5, "minY": 115.25, "maxX": 534.0, "maxY": 626.0}, "class_id": 11, "box_caption": "B 0.009", "scores": {"class_score": 0.009429931640625}, "domain": "pixel"}, {"position": {"minX": 142.25, "minY": 117.0, "maxX": 532.0, "maxY": 624.5}, "class_id": 33, "box_caption": "X 0.009", "scores": {"class_score": 0.0094146728515625}, "domain": "pixel"}, {"position": {"minX": -1.6875, "minY": -1.875, "maxX": 216.5, "maxY": 360.5}, "class_id": 29, "box_caption": "T 0.009", "scores": {"class_score": 0.00940704345703125}, "domain": "pixel"}, {"position": {"minX": -1.6875, "minY": -1.875, "maxX": 216.5, "maxY": 360.5}, "class_id": 12, "box_caption": "C 0.009", "scores": {"class_score": 0.00939178466796875}, "domain": "pixel"}, {"position": {"minX": -1.6875, "minY": -1.875, "maxX": 216.5, "maxY": 360.5}, "class_id": 18, "box_caption": "I 0.009", "scores": {"class_score": 0.00939178466796875}, "domain": "pixel"}, {"position": {"minX": 139.5, "minY": 115.25, "maxX": 534.0, "maxY": 626.0}, "class_id": 31, "box_caption": "V 0.009", "scores": {"class_score": 0.00939178466796875}, "domain": "pixel"}, {"position": {"minX": -1.6875, "minY": -1.875, "maxX": 216.5, "maxY": 360.5}, "class_id": 8, "box_caption": "8 0.009", "scores": {"class_score": 0.00937652587890625}, "domain": "pixel"}, {"position": {"minX": -1.6875, "minY": -1.875, "maxX": 216.5, "maxY": 360.5}, "class_id": 15, "box_caption": "F 0.009", "scores": {"class_score": 0.00937652587890625}, "domain": "pixel"}, {"position": {"minX": 139.5, "minY": 115.25, "maxX": 534.0, "maxY": 626.0}, "class_id": 39, "box_caption": "e 0.009", "scores": {"class_score": 0.00936126708984375}, "domain": "pixel"}, {"position": {"minX": -2.375, "minY": -0.625, "maxX": 216.875, "maxY": 358.0}, "class_id": 10, "box_caption": "A 0.009", "scores": {"class_score": 0.0093536376953125}, "domain": "pixel"}, {"position": {"minX": -2.375, "minY": -0.625, "maxX": 216.875, "maxY": 358.0}, "class_id": 38, "box_caption": "d 0.009", "scores": {"class_score": 0.00933074951171875}, "domain": "pixel"}, {"position": {"minX": 299.0, "minY": 335.0, "maxX": 691.0, "maxY": 662.5}, "class_id": 1, "box_caption": "1 0.009", "scores": {"class_score": 0.00933074951171875}, "domain": "pixel"}, {"position": {"minX": 139.5, "minY": 115.25, "maxX": 534.0, "maxY": 626.0}, "class_id": 15, "box_caption": "F 0.009", "scores": {"class_score": 0.0093231201171875}, "domain": "pixel"}, {"position": {"minX": 139.5, "minY": 115.25, "maxX": 534.0, "maxY": 626.0}, "class_id": 46, "box_caption": "t 0.009", "scores": {"class_score": 0.009307861328125}, "domain": "pixel"}, {"position": {"minX": 299.0, "minY": 335.0, "maxX": 691.0, "maxY": 662.5}, "class_id": 9, "box_caption": "9 0.009", "scores": {"class_score": 0.009307861328125}, "domain": "pixel"}, {"position": {"minX": 299.25, "minY": 333.75, "maxX": 692.0, "maxY": 662.0}, "class_id": 38, "box_caption": "d 0.009", "scores": {"class_score": 0.00930023193359375}, "domain": "pixel"}, {"position": {"minX": 299.0, "minY": 335.0, "maxX": 691.0, "maxY": 662.5}, "class_id": 20, "box_caption": "K 0.009", "scores": {"class_score": 0.00927734375}, "domain": "pixel"}, {"position": {"minX": 299.25, "minY": 333.75, "maxX": 692.0, "maxY": 662.0}, "class_id": 29, "box_caption": "T 0.009", "scores": {"class_score": 0.0092620849609375}, "domain": "pixel"}, {"position": {"minX": 142.25, "minY": 117.0, "maxX": 532.0, "maxY": 624.5}, "class_id": 23, "box_caption": "N 0.009", "scores": {"class_score": 0.00925445556640625}, "domain": "pixel"}, {"position": {"minX": 139.5, "minY": 115.25, "maxX": 534.0, "maxY": 626.0}, "class_id": 2, "box_caption": "2 0.009", "scores": {"class_score": 0.00925445556640625}, "domain": "pixel"}, {"position": {"minX": -1.6875, "minY": -1.875, "maxX": 216.5, "maxY": 360.5}, "class_id": 21, "box_caption": "L 0.009", "scores": {"class_score": 0.009246826171875}, "domain": "pixel"}, {"position": {"minX": -1.6875, "minY": -1.875, "maxX": 216.5, "maxY": 360.5}, "class_id": 41, "box_caption": "g 0.009", "scores": {"class_score": 0.009246826171875}, "domain": "pixel"}, {"position": {"minX": 139.5, "minY": 115.25, "maxX": 534.0, "maxY": 626.0}, "class_id": 6, "box_caption": "6 0.009", "scores": {"class_score": 0.0092315673828125}, "domain": "pixel"}, {"position": {"minX": -2.375, "minY": -0.625, "maxX": 216.875, "maxY": 358.0}, "class_id": 28, "box_caption": "S 0.009", "scores": {"class_score": 0.00922393798828125}, "domain": "pixel"}, {"position": {"minX": -1.6875, "minY": -1.875, "maxX": 216.5, "maxY": 360.5}, "class_id": 31, "box_caption": "V 0.009", "scores": {"class_score": 0.00919342041015625}, "domain": "pixel"}, {"position": {"minX": -2.375, "minY": -0.625, "maxX": 216.875, "maxY": 358.0}, "class_id": 4, "box_caption": "4 0.009", "scores": {"class_score": 0.00919342041015625}, "domain": "pixel"}, {"position": {"minX": 139.5, "minY": 115.25, "maxX": 534.0, "maxY": 626.0}, "class_id": 17, "box_caption": "H 0.009", "scores": {"class_score": 0.00916290283203125}, "domain": "pixel"}, {"position": {"minX": 299.25, "minY": 333.75, "maxX": 692.0, "maxY": 662.0}, "class_id": 32, "box_caption": "W 0.009", "scores": {"class_score": 0.009124755859375}, "domain": "pixel"}, {"position": {"minX": 139.5, "minY": 115.25, "maxX": 534.0, "maxY": 626.0}, "class_id": 45, "box_caption": "r 0.009", "scores": {"class_score": 0.0090789794921875}, "domain": "pixel"}, {"position": {"minX": 139.5, "minY": 115.25, "maxX": 534.0, "maxY": 626.0}, "class_id": 14, "box_caption": "E 0.009", "scores": {"class_score": 0.00902557373046875}, "domain": "pixel"}, {"position": {"minX": -1.6875, "minY": -1.875, "maxX": 216.5, "maxY": 360.5}, "class_id": 1, "box_caption": "1 0.009", "scores": {"class_score": 0.009002685546875}, "domain": "pixel"}, {"position": {"minX": -1.6875, "minY": -1.875, "maxX": 216.5, "maxY": 360.5}, "class_id": 45, "box_caption": "r 0.009", "scores": {"class_score": 0.0089874267578125}, "domain": "pixel"}, {"position": {"minX": 142.25, "minY": 117.0, "maxX": 532.0, "maxY": 624.5}, "class_id": 24, "box_caption": "O 0.009", "scores": {"class_score": 0.0089874267578125}, "domain": "pixel"}, {"position": {"minX": 139.5, "minY": 115.25, "maxX": 534.0, "maxY": 626.0}, "class_id": 25, "box_caption": "P 0.009", "scores": {"class_score": 0.00897979736328125}, "domain": "pixel"}, {"position": {"minX": 299.0, "minY": 335.0, "maxX": 691.0, "maxY": 662.5}, "class_id": 7, "box_caption": "7 0.009", "scores": {"class_score": 0.0089569091796875}, "domain": "pixel"}, {"position": {"minX": 139.5, "minY": 115.25, "maxX": 534.0, "maxY": 626.0}, "class_id": 34, "box_caption": "Y 0.009", "scores": {"class_score": 0.008941650390625}, "domain": "pixel"}, {"position": {"minX": 139.5, "minY": 115.25, "maxX": 534.0, "maxY": 626.0}, "class_id": 44, "box_caption": "q 0.009", "scores": {"class_score": 0.00891876220703125}, "domain": "pixel"}, {"position": {"minX": -2.375, "minY": -0.625, "maxX": 216.875, "maxY": 358.0}, "class_id": 44, "box_caption": "q 0.009", "scores": {"class_score": 0.008880615234375}, "domain": "pixel"}, {"position": {"minX": 142.25, "minY": 117.0, "maxX": 532.0, "maxY": 624.5}, "class_id": 35, "box_caption": "Z 0.009", "scores": {"class_score": 0.0088348388671875}, "domain": "pixel"}, {"position": {"minX": 139.5, "minY": 115.25, "maxX": 534.0, "maxY": 626.0}, "class_id": 41, "box_caption": "g 0.009", "scores": {"class_score": 0.008819580078125}, "domain": "pixel"}, {"position": {"minX": 142.25, "minY": 117.0, "maxX": 532.0, "maxY": 624.5}, "class_id": 32, "box_caption": "W 0.009", "scores": {"class_score": 0.0087890625}, "domain": "pixel"}, {"position": {"minX": 139.5, "minY": 115.25, "maxX": 534.0, "maxY": 626.0}, "class_id": 8, "box_caption": "8 0.009", "scores": {"class_score": 0.0087890625}, "domain": "pixel"}, {"position": {"minX": 299.25, "minY": 333.75, "maxX": 692.0, "maxY": 662.0}, "class_id": 40, "box_caption": "f 0.009", "scores": {"class_score": 0.0087738037109375}, "domain": "pixel"}, {"position": {"minX": 139.5, "minY": 115.25, "maxX": 534.0, "maxY": 626.0}, "class_id": 10, "box_caption": "A 0.009", "scores": {"class_score": 0.00875091552734375}, "domain": "pixel"}, {"position": {"minX": 139.5, "minY": 115.25, "maxX": 534.0, "maxY": 626.0}, "class_id": 12, "box_caption": "C 0.009", "scores": {"class_score": 0.00873565673828125}, "domain": "pixel"}, {"position": {"minX": 139.5, "minY": 115.25, "maxX": 534.0, "maxY": 626.0}, "class_id": 29, "box_caption": "T 0.009", "scores": {"class_score": 0.0085601806640625}, "domain": "pixel"}, {"position": {"minX": 299.0, "minY": 335.0, "maxX": 691.0, "maxY": 662.5}, "class_id": 21, "box_caption": "L 0.009", "scores": {"class_score": 0.0085601806640625}, "domain": "pixel"}, {"position": {"minX": 326.0, "minY": 385.75, "maxX": 601.5, "maxY": 667.0}, "class_id": 9, "box_caption": "9 0.009", "scores": {"class_score": 0.00855255126953125}, "domain": "pixel"}, {"position": {"minX": 139.5, "minY": 115.25, "maxX": 534.0, "maxY": 626.0}, "class_id": 28, "box_caption": "S 0.009", "scores": {"class_score": 0.00853729248046875}, "domain": "pixel"}, {"position": {"minX": 142.25, "minY": 117.0, "maxX": 532.0, "maxY": 624.5}, "class_id": 43, "box_caption": "n 0.009", "scores": {"class_score": 0.00852203369140625}, "domain": "pixel"}, {"position": {"minX": 142.25, "minY": 117.0, "maxX": 532.0, "maxY": 624.5}, "class_id": 22, "box_caption": "M 0.009", "scores": {"class_score": 0.00850677490234375}, "domain": "pixel"}, {"position": {"minX": 139.5, "minY": 115.25, "maxX": 534.0, "maxY": 626.0}, "class_id": 19, "box_caption": "J 0.009", "scores": {"class_score": 0.00850677490234375}, "domain": "pixel"}, {"position": {"minX": 32.0625, "minY": 78.875, "maxX": 195.5, "maxY": 334.5}, "class_id": 9, "box_caption": "9 0.008", "scores": {"class_score": 0.0084991455078125}, "domain": "pixel"}, {"position": {"minX": 326.0, "minY": 385.75, "maxX": 601.5, "maxY": 667.0}, "class_id": 37, "box_caption": "b 0.008", "scores": {"class_score": 0.0084991455078125}, "domain": "pixel"}, {"position": {"minX": 139.5, "minY": 115.25, "maxX": 534.0, "maxY": 626.0}, "class_id": 20, "box_caption": "K 0.008", "scores": {"class_score": 0.00847625732421875}, "domain": "pixel"}, {"position": {"minX": 32.0625, "minY": 78.875, "maxX": 195.5, "maxY": 334.5}, "class_id": 12, "box_caption": "C 0.008", "scores": {"class_score": 0.0084228515625}, "domain": "pixel"}, {"position": {"minX": 139.5, "minY": 115.25, "maxX": 534.0, "maxY": 626.0}, "class_id": 40, "box_caption": "f 0.008", "scores": {"class_score": 0.008392333984375}, "domain": "pixel"}, {"position": {"minX": 142.25, "minY": 117.0, "maxX": 532.0, "maxY": 624.5}, "class_id": 18, "box_caption": "I 0.008", "scores": {"class_score": 0.00836181640625}, "domain": "pixel"}, {"position": {"minX": 142.25, "minY": 117.0, "maxX": 532.0, "maxY": 624.5}, "class_id": 4, "box_caption": "4 0.008", "scores": {"class_score": 0.0083465576171875}, "domain": "pixel"}, {"position": {"minX": 139.5, "minY": 115.25, "maxX": 534.0, "maxY": 626.0}, "class_id": 42, "box_caption": "h 0.008", "scores": {"class_score": 0.0083465576171875}, "domain": "pixel"}, {"position": {"minX": 32.0625, "minY": 78.875, "maxX": 195.5, "maxY": 334.5}, "class_id": 17, "box_caption": "H 0.008", "scores": {"class_score": 0.00833892822265625}, "domain": "pixel"}, {"position": {"minX": 142.25, "minY": 117.0, "maxX": 532.0, "maxY": 624.5}, "class_id": 38, "box_caption": "d 0.008", "scores": {"class_score": 0.0082855224609375}, "domain": "pixel"}, {"position": {"minX": 142.25, "minY": 117.0, "maxX": 532.0, "maxY": 624.5}, "class_id": 37, "box_caption": "b 0.008", "scores": {"class_score": 0.00818634033203125}, "domain": "pixel"}, {"position": {"minX": 139.5, "minY": 115.25, "maxX": 534.0, "maxY": 626.0}, "class_id": 9, "box_caption": "9 0.008", "scores": {"class_score": 0.00815582275390625}, "domain": "pixel"}, {"position": {"minX": 32.0625, "minY": 78.875, "maxX": 195.5, "maxY": 334.5}, "class_id": 38, "box_caption": "d 0.008", "scores": {"class_score": 0.008148193359375}, "domain": "pixel"}, {"position": {"minX": 32.0625, "minY": 78.875, "maxX": 195.5, "maxY": 334.5}, "class_id": 6, "box_caption": "6 0.008", "scores": {"class_score": 0.0081024169921875}, "domain": "pixel"}, {"position": {"minX": 142.25, "minY": 117.0, "maxX": 532.0, "maxY": 624.5}, "class_id": 21, "box_caption": "L 0.008", "scores": {"class_score": 0.00809478759765625}, "domain": "pixel"}, {"position": {"minX": 139.5, "minY": 115.25, "maxX": 534.0, "maxY": 626.0}, "class_id": 36, "box_caption": "a 0.008", "scores": {"class_score": 0.00809478759765625}, "domain": "pixel"}, {"position": {"minX": 379.25, "minY": 439.75, "maxX": 678.0, "maxY": 671.5}, "class_id": 38, "box_caption": "d 0.008", "scores": {"class_score": 0.00807952880859375}, "domain": "pixel"}, {"position": {"minX": 326.0, "minY": 385.75, "maxX": 601.5, "maxY": 667.0}, "class_id": 2, "box_caption": "2 0.008", "scores": {"class_score": 0.0080718994140625}, "domain": "pixel"}, {"position": {"minX": 32.0625, "minY": 78.875, "maxX": 195.5, "maxY": 334.5}, "class_id": 23, "box_caption": "N 0.008", "scores": {"class_score": 0.008056640625}, "domain": "pixel"}, {"position": {"minX": 378.0, "minY": 440.25, "maxX": 679.0, "maxY": 671.0}, "class_id": 30, "box_caption": "U 0.008", "scores": {"class_score": 0.008056640625}, "domain": "pixel"}, {"position": {"minX": 326.0, "minY": 385.75, "maxX": 601.5, "maxY": 667.0}, "class_id": 42, "box_caption": "h 0.008", "scores": {"class_score": 0.0080413818359375}, "domain": "pixel"}, {"position": {"minX": 32.0625, "minY": 78.875, "maxX": 195.5, "maxY": 334.5}, "class_id": 37, "box_caption": "b 0.008", "scores": {"class_score": 0.0080108642578125}, "domain": "pixel"}, {"position": {"minX": 326.0, "minY": 385.75, "maxX": 601.5, "maxY": 667.0}, "class_id": 15, "box_caption": "F 0.008", "scores": {"class_score": 0.0080108642578125}, "domain": "pixel"}, {"position": {"minX": 326.0, "minY": 385.75, "maxX": 601.5, "maxY": 667.0}, "class_id": 12, "box_caption": "C 0.008", "scores": {"class_score": 0.00799560546875}, "domain": "pixel"}, {"position": {"minX": 142.25, "minY": 117.0, "maxX": 532.0, "maxY": 624.5}, "class_id": 1, "box_caption": "1 0.008", "scores": {"class_score": 0.00797271728515625}, "domain": "pixel"}, {"position": {"minX": 32.0625, "minY": 78.875, "maxX": 195.5, "maxY": 334.5}, "class_id": 43, "box_caption": "n 0.008", "scores": {"class_score": 0.007965087890625}, "domain": "pixel"}, {"position": {"minX": 376.0, "minY": 438.25, "maxX": 678.0, "maxY": 670.0}, "class_id": 10, "box_caption": "A 0.008", "scores": {"class_score": 0.0079498291015625}, "domain": "pixel"}, {"position": {"minX": 378.0, "minY": 440.25, "maxX": 679.0, "maxY": 671.0}, "class_id": 41, "box_caption": "g 0.008", "scores": {"class_score": 0.0079345703125}, "domain": "pixel"}, {"position": {"minX": 32.0625, "minY": 78.875, "maxX": 195.5, "maxY": 334.5}, "class_id": 30, "box_caption": "U 0.008", "scores": {"class_score": 0.007904052734375}, "domain": "pixel"}, {"position": {"minX": 376.0, "minY": 438.25, "maxX": 678.0, "maxY": 670.0}, "class_id": 27, "box_caption": "R 0.008", "scores": {"class_score": 0.007904052734375}, "domain": "pixel"}, {"position": {"minX": 376.0, "minY": 438.25, "maxX": 678.0, "maxY": 670.0}, "class_id": 26, "box_caption": "Q 0.008", "scores": {"class_score": 0.00789642333984375}, "domain": "pixel"}, {"position": {"minX": 32.0625, "minY": 78.875, "maxX": 195.5, "maxY": 334.5}, "class_id": 4, "box_caption": "4 0.008", "scores": {"class_score": 0.0078887939453125}, "domain": "pixel"}, {"position": {"minX": 32.0625, "minY": 78.875, "maxX": 195.5, "maxY": 334.5}, "class_id": 7, "box_caption": "7 0.008", "scores": {"class_score": 0.0078887939453125}, "domain": "pixel"}, {"position": {"minX": 32.0625, "minY": 78.875, "maxX": 195.5, "maxY": 334.5}, "class_id": 14, "box_caption": "E 0.008", "scores": {"class_score": 0.0078887939453125}, "domain": "pixel"}, {"position": {"minX": 32.0625, "minY": 78.875, "maxX": 195.5, "maxY": 334.5}, "class_id": 42, "box_caption": "h 0.008", "scores": {"class_score": 0.0078887939453125}, "domain": "pixel"}, {"position": {"minX": 326.0, "minY": 385.75, "maxX": 601.5, "maxY": 667.0}, "class_id": 30, "box_caption": "U 0.008", "scores": {"class_score": 0.0078887939453125}, "domain": "pixel"}, {"position": {"minX": 378.0, "minY": 440.25, "maxX": 679.0, "maxY": 671.0}, "class_id": 14, "box_caption": "E 0.008", "scores": {"class_score": 0.0078887939453125}, "domain": "pixel"}, {"position": {"minX": 378.0, "minY": 440.25, "maxX": 679.0, "maxY": 671.0}, "class_id": 37, "box_caption": "b 0.008", "scores": {"class_score": 0.0078887939453125}, "domain": "pixel"}, {"position": {"minX": 32.0625, "minY": 78.875, "maxX": 195.5, "maxY": 334.5}, "class_id": 5, "box_caption": "5 0.008", "scores": {"class_score": 0.00787353515625}, "domain": "pixel"}, {"position": {"minX": 32.0625, "minY": 78.875, "maxX": 195.5, "maxY": 334.5}, "class_id": 15, "box_caption": "F 0.008", "scores": {"class_score": 0.0078582763671875}, "domain": "pixel"}, {"position": {"minX": 326.0, "minY": 385.75, "maxX": 601.5, "maxY": 667.0}, "class_id": 38, "box_caption": "d 0.008", "scores": {"class_score": 0.0078582763671875}, "domain": "pixel"}, {"position": {"minX": 378.0, "minY": 440.25, "maxX": 679.0, "maxY": 671.0}, "class_id": 8, "box_caption": "8 0.008", "scores": {"class_score": 0.00785064697265625}, "domain": "pixel"}, {"position": {"minX": 326.0, "minY": 385.75, "maxX": 601.5, "maxY": 667.0}, "class_id": 19, "box_caption": "J 0.008", "scores": {"class_score": 0.007843017578125}, "domain": "pixel"}, {"position": {"minX": 32.0625, "minY": 78.875, "maxX": 195.5, "maxY": 334.5}, "class_id": 40, "box_caption": "f 0.008", "scores": {"class_score": 0.0078277587890625}, "domain": "pixel"}, {"position": {"minX": 326.0, "minY": 385.75, "maxX": 601.5, "maxY": 667.0}, "class_id": 17, "box_caption": "H 0.008", "scores": {"class_score": 0.0078125}, "domain": "pixel"}, {"position": {"minX": 378.0, "minY": 440.25, "maxX": 679.0, "maxY": 671.0}, "class_id": 3, "box_caption": "3 0.008", "scores": {"class_score": 0.00780487060546875}, "domain": "pixel"}, {"position": {"minX": 326.0, "minY": 385.75, "maxX": 601.5, "maxY": 667.0}, "class_id": 26, "box_caption": "Q 0.008", "scores": {"class_score": 0.007801055908203125}, "domain": "pixel"}, {"position": {"minX": 379.25, "minY": 439.75, "maxX": 678.0, "maxY": 671.5}, "class_id": 5, "box_caption": "5 0.008", "scores": {"class_score": 0.00778961181640625}, "domain": "pixel"}, {"position": {"minX": 326.0, "minY": 385.75, "maxX": 601.5, "maxY": 667.0}, "class_id": 3, "box_caption": "3 0.008", "scores": {"class_score": 0.0077667236328125}, "domain": "pixel"}, {"position": {"minX": 32.0625, "minY": 78.875, "maxX": 195.5, "maxY": 334.5}, "class_id": 22, "box_caption": "M 0.008", "scores": {"class_score": 0.007755279541015625}, "domain": "pixel"}, {"position": {"minX": 326.0, "minY": 385.75, "maxX": 601.5, "maxY": 667.0}, "class_id": 35, "box_caption": "Z 0.008", "scores": {"class_score": 0.007755279541015625}, "domain": "pixel"}, {"position": {"minX": 326.0, "minY": 385.75, "maxX": 601.5, "maxY": 667.0}, "class_id": 5, "box_caption": "5 0.008", "scores": {"class_score": 0.007740020751953125}, "domain": "pixel"}, {"position": {"minX": 32.0625, "minY": 78.875, "maxX": 195.5, "maxY": 334.5}, "class_id": 13, "box_caption": "D 0.008", "scores": {"class_score": 0.0077362060546875}, "domain": "pixel"}, {"position": {"minX": 32.0625, "minY": 78.875, "maxX": 195.5, "maxY": 334.5}, "class_id": 41, "box_caption": "g 0.008", "scores": {"class_score": 0.0077362060546875}, "domain": "pixel"}, {"position": {"minX": 326.0, "minY": 385.75, "maxX": 601.5, "maxY": 667.0}, "class_id": 39, "box_caption": "e 0.008", "scores": {"class_score": 0.007724761962890625}, "domain": "pixel"}, {"position": {"minX": 326.0, "minY": 385.75, "maxX": 601.5, "maxY": 667.0}, "class_id": 0, "box_caption": "0 0.008", "scores": {"class_score": 0.007709503173828125}, "domain": "pixel"}, {"position": {"minX": 326.0, "minY": 385.75, "maxX": 601.5, "maxY": 667.0}, "class_id": 10, "box_caption": "A 0.008", "scores": {"class_score": 0.00769805908203125}, "domain": "pixel"}, {"position": {"minX": 32.0625, "minY": 78.875, "maxX": 195.5, "maxY": 334.5}, "class_id": 28, "box_caption": "S 0.008", "scores": {"class_score": 0.007694244384765625}, "domain": "pixel"}, {"position": {"minX": 32.0625, "minY": 78.875, "maxX": 195.5, "maxY": 334.5}, "class_id": 35, "box_caption": "Z 0.008", "scores": {"class_score": 0.00768280029296875}, "domain": "pixel"}, {"position": {"minX": 376.0, "minY": 438.25, "maxX": 678.0, "maxY": 670.0}, "class_id": 15, "box_caption": "F 0.008", "scores": {"class_score": 0.0076751708984375}, "domain": "pixel"}, {"position": {"minX": 326.0, "minY": 385.75, "maxX": 601.5, "maxY": 667.0}, "class_id": 23, "box_caption": "N 0.008", "scores": {"class_score": 0.00766754150390625}, "domain": "pixel"}, {"position": {"minX": 326.0, "minY": 385.75, "maxX": 601.5, "maxY": 667.0}, "class_id": 34, "box_caption": "Y 0.008", "scores": {"class_score": 0.00766754150390625}, "domain": "pixel"}, {"position": {"minX": 379.25, "minY": 439.75, "maxX": 678.0, "maxY": 671.5}, "class_id": 17, "box_caption": "H 0.008", "scores": {"class_score": 0.00765228271484375}, "domain": "pixel"}, {"position": {"minX": 379.25, "minY": 439.75, "maxX": 678.0, "maxY": 671.5}, "class_id": 34, "box_caption": "Y 0.008", "scores": {"class_score": 0.00763702392578125}, "domain": "pixel"}, {"position": {"minX": 376.0, "minY": 438.25, "maxX": 678.0, "maxY": 670.0}, "class_id": 36, "box_caption": "a 0.008", "scores": {"class_score": 0.00762939453125}, "domain": "pixel"}, {"position": {"minX": 378.0, "minY": 440.25, "maxX": 679.0, "maxY": 671.0}, "class_id": 35, "box_caption": "Z 0.008", "scores": {"class_score": 0.007625579833984375}, "domain": "pixel"}, {"position": {"minX": 326.0, "minY": 385.75, "maxX": 601.5, "maxY": 667.0}, "class_id": 22, "box_caption": "M 0.008", "scores": {"class_score": 0.00762176513671875}, "domain": "pixel"}, {"position": {"minX": 326.0, "minY": 385.75, "maxX": 601.5, "maxY": 667.0}, "class_id": 45, "box_caption": "r 0.008", "scores": {"class_score": 0.00762176513671875}, "domain": "pixel"}, {"position": {"minX": 32.0625, "minY": 78.875, "maxX": 195.5, "maxY": 334.5}, "class_id": 24, "box_caption": "O 0.008", "scores": {"class_score": 0.007617950439453125}, "domain": "pixel"}, {"position": {"minX": 32.0625, "minY": 78.875, "maxX": 195.5, "maxY": 334.5}, "class_id": 36, "box_caption": "a 0.008", "scores": {"class_score": 0.007617950439453125}, "domain": "pixel"}, {"position": {"minX": 379.25, "minY": 439.75, "maxX": 678.0, "maxY": 671.5}, "class_id": 2, "box_caption": "2 0.008", "scores": {"class_score": 0.007610321044921875}, "domain": "pixel"}, {"position": {"minX": 378.0, "minY": 440.25, "maxX": 679.0, "maxY": 671.0}, "class_id": 42, "box_caption": "h 0.008", "scores": {"class_score": 0.007610321044921875}, "domain": "pixel"}, {"position": {"minX": 32.0625, "minY": 78.875, "maxX": 195.5, "maxY": 334.5}, "class_id": 16, "box_caption": "G 0.008", "scores": {"class_score": 0.00760650634765625}, "domain": "pixel"}, {"position": {"minX": 32.0625, "minY": 78.875, "maxX": 195.5, "maxY": 334.5}, "class_id": 20, "box_caption": "K 0.008", "scores": {"class_score": 0.00760650634765625}, "domain": "pixel"}, {"position": {"minX": 326.0, "minY": 385.75, "maxX": 601.5, "maxY": 667.0}, "class_id": 32, "box_caption": "W 0.008", "scores": {"class_score": 0.00760650634765625}, "domain": "pixel"}, {"position": {"minX": 326.0, "minY": 385.75, "maxX": 601.5, "maxY": 667.0}, "class_id": 33, "box_caption": "X 0.008", "scores": {"class_score": 0.00760650634765625}, "domain": "pixel"}, {"position": {"minX": 326.0, "minY": 385.75, "maxX": 601.5, "maxY": 667.0}, "class_id": 40, "box_caption": "f 0.008", "scores": {"class_score": 0.007595062255859375}, "domain": "pixel"}, {"position": {"minX": 32.0625, "minY": 78.875, "maxX": 195.5, "maxY": 334.5}, "class_id": 0, "box_caption": "0 0.008", "scores": {"class_score": 0.007579803466796875}, "domain": "pixel"}, {"position": {"minX": 32.0625, "minY": 78.875, "maxX": 195.5, "maxY": 334.5}, "class_id": 26, "box_caption": "Q 0.008", "scores": {"class_score": 0.007579803466796875}, "domain": "pixel"}, {"position": {"minX": 326.0, "minY": 385.75, "maxX": 601.5, "maxY": 667.0}, "class_id": 46, "box_caption": "t 0.008", "scores": {"class_score": 0.007579803466796875}, "domain": "pixel"}, {"position": {"minX": 379.25, "minY": 439.75, "maxX": 678.0, "maxY": 671.5}, "class_id": 18, "box_caption": "I 0.008", "scores": {"class_score": 0.007568359375}, "domain": "pixel"}, {"position": {"minX": 378.0, "minY": 440.25, "maxX": 679.0, "maxY": 671.0}, "class_id": 33, "box_caption": "X 0.008", "scores": {"class_score": 0.0075531005859375}, "domain": "pixel"}, {"position": {"minX": 326.0, "minY": 385.75, "maxX": 601.5, "maxY": 667.0}, "class_id": 6, "box_caption": "6 0.008", "scores": {"class_score": 0.007549285888671875}, "domain": "pixel"}, {"position": {"minX": 326.0, "minY": 385.75, "maxX": 601.5, "maxY": 667.0}, "class_id": 43, "box_caption": "n 0.008", "scores": {"class_score": 0.007549285888671875}, "domain": "pixel"}, {"position": {"minX": 326.0, "minY": 385.75, "maxX": 601.5, "maxY": 667.0}, "class_id": 18, "box_caption": "I 0.008", "scores": {"class_score": 0.007537841796875}, "domain": "pixel"}, {"position": {"minX": 378.0, "minY": 440.25, "maxX": 679.0, "maxY": 671.0}, "class_id": 4, "box_caption": "4 0.008", "scores": {"class_score": 0.007537841796875}, "domain": "pixel"}, {"position": {"minX": 32.0625, "minY": 78.875, "maxX": 195.5, "maxY": 334.5}, "class_id": 11, "box_caption": "B 0.008", "scores": {"class_score": 0.007534027099609375}, "domain": "pixel"}, {"position": {"minX": 32.0625, "minY": 78.875, "maxX": 195.5, "maxY": 334.5}, "class_id": 27, "box_caption": "R 0.008", "scores": {"class_score": 0.007534027099609375}, "domain": "pixel"}, {"position": {"minX": 378.0, "minY": 440.25, "maxX": 679.0, "maxY": 671.0}, "class_id": 31, "box_caption": "V 0.008", "scores": {"class_score": 0.007526397705078125}, "domain": "pixel"}, {"position": {"minX": 378.0, "minY": 440.25, "maxX": 679.0, "maxY": 671.0}, "class_id": 46, "box_caption": "t 0.008", "scores": {"class_score": 0.007526397705078125}, "domain": "pixel"}, {"position": {"minX": 32.0625, "minY": 78.875, "maxX": 195.5, "maxY": 334.5}, "class_id": 2, "box_caption": "2 0.008", "scores": {"class_score": 0.0075225830078125}, "domain": "pixel"}, {"position": {"minX": 32.0625, "minY": 78.875, "maxX": 195.5, "maxY": 334.5}, "class_id": 10, "box_caption": "A 0.008", "scores": {"class_score": 0.0075225830078125}, "domain": "pixel"}, {"position": {"minX": 326.0, "minY": 385.75, "maxX": 601.5, "maxY": 667.0}, "class_id": 16, "box_caption": "G 0.008", "scores": {"class_score": 0.007503509521484375}, "domain": "pixel"}, {"position": {"minX": 326.0, "minY": 385.75, "maxX": 601.5, "maxY": 667.0}, "class_id": 28, "box_caption": "S 0.008", "scores": {"class_score": 0.007503509521484375}, "domain": "pixel"}, {"position": {"minX": 376.0, "minY": 438.25, "maxX": 678.0, "maxY": 670.0}, "class_id": 0, "box_caption": "0 0.007", "scores": {"class_score": 0.00749969482421875}, "domain": "pixel"}, {"position": {"minX": 326.0, "minY": 385.75, "maxX": 601.5, "maxY": 667.0}, "class_id": 14, "box_caption": "E 0.007", "scores": {"class_score": 0.007495880126953125}, "domain": "pixel"}, {"position": {"minX": 32.0625, "minY": 78.875, "maxX": 195.5, "maxY": 334.5}, "class_id": 29, "box_caption": "T 0.007", "scores": {"class_score": 0.007488250732421875}, "domain": "pixel"}, {"position": {"minX": 379.25, "minY": 439.75, "maxX": 678.0, "maxY": 671.5}, "class_id": 39, "box_caption": "e 0.007", "scores": {"class_score": 0.00748443603515625}, "domain": "pixel"}, {"position": {"minX": 32.0625, "minY": 78.875, "maxX": 195.5, "maxY": 334.5}, "class_id": 8, "box_caption": "8 0.007", "scores": {"class_score": 0.007476806640625}, "domain": "pixel"}, {"position": {"minX": 32.0625, "minY": 78.875, "maxX": 195.5, "maxY": 334.5}, "class_id": 45, "box_caption": "r 0.007", "scores": {"class_score": 0.007476806640625}, "domain": "pixel"}, {"position": {"minX": 326.0, "minY": 385.75, "maxX": 601.5, "maxY": 667.0}, "class_id": 36, "box_caption": "a 0.007", "scores": {"class_score": 0.007476806640625}, "domain": "pixel"}, {"position": {"minX": 379.25, "minY": 439.75, "maxX": 678.0, "maxY": 671.5}, "class_id": 9, "box_caption": "9 0.007", "scores": {"class_score": 0.00746917724609375}, "domain": "pixel"}, {"position": {"minX": 326.0, "minY": 385.75, "maxX": 601.5, "maxY": 667.0}, "class_id": 7, "box_caption": "7 0.007", "scores": {"class_score": 0.0074615478515625}, "domain": "pixel"}, {"position": {"minX": 326.0, "minY": 385.75, "maxX": 601.5, "maxY": 667.0}, "class_id": 20, "box_caption": "K 0.007", "scores": {"class_score": 0.0074615478515625}, "domain": "pixel"}, {"position": {"minX": 379.25, "minY": 439.75, "maxX": 678.0, "maxY": 671.5}, "class_id": 32, "box_caption": "W 0.007", "scores": {"class_score": 0.00745391845703125}, "domain": "pixel"}, {"position": {"minX": 378.0, "minY": 440.25, "maxX": 679.0, "maxY": 671.0}, "class_id": 16, "box_caption": "G 0.007", "scores": {"class_score": 0.00745391845703125}, "domain": "pixel"}, {"position": {"minX": 32.0625, "minY": 78.875, "maxX": 195.5, "maxY": 334.5}, "class_id": 32, "box_caption": "W 0.007", "scores": {"class_score": 0.007450103759765625}, "domain": "pixel"}, {"position": {"minX": 326.0, "minY": 385.75, "maxX": 601.5, "maxY": 667.0}, "class_id": 11, "box_caption": "B 0.007", "scores": {"class_score": 0.007434844970703125}, "domain": "pixel"}, {"position": {"minX": 32.0625, "minY": 78.875, "maxX": 195.5, "maxY": 334.5}, "class_id": 33, "box_caption": "X 0.007", "scores": {"class_score": 0.00742340087890625}, "domain": "pixel"}, {"position": {"minX": 326.0, "minY": 385.75, "maxX": 601.5, "maxY": 667.0}, "class_id": 13, "box_caption": "D 0.007", "scores": {"class_score": 0.007419586181640625}, "domain": "pixel"}, {"position": {"minX": 378.0, "minY": 440.25, "maxX": 679.0, "maxY": 671.0}, "class_id": 25, "box_caption": "P 0.007", "scores": {"class_score": 0.007411956787109375}, "domain": "pixel"}, {"position": {"minX": 376.0, "minY": 438.25, "maxX": 678.0, "maxY": 670.0}, "class_id": 23, "box_caption": "N 0.007", "scores": {"class_score": 0.0074005126953125}, "domain": "pixel"}, {"position": {"minX": 32.0625, "minY": 78.875, "maxX": 195.5, "maxY": 334.5}, "class_id": 34, "box_caption": "Y 0.007", "scores": {"class_score": 0.00739288330078125}, "domain": "pixel"}, {"position": {"minX": 7.875, "minY": 6.25, "maxX": 409.5, "maxY": 531.0}, "class_id": 17, "box_caption": "H 0.007", "scores": {"class_score": 0.00738525390625}, "domain": "pixel"}, {"position": {"minX": 378.0, "minY": 440.25, "maxX": 679.0, "maxY": 671.0}, "class_id": 22, "box_caption": "M 0.007", "scores": {"class_score": 0.007343292236328125}, "domain": "pixel"}, {"position": {"minX": 326.0, "minY": 385.75, "maxX": 601.5, "maxY": 667.0}, "class_id": 24, "box_caption": "O 0.007", "scores": {"class_score": 0.00732421875}, "domain": "pixel"}, {"position": {"minX": 326.0, "minY": 385.75, "maxX": 601.5, "maxY": 667.0}, "class_id": 27, "box_caption": "R 0.007", "scores": {"class_score": 0.007305145263671875}, "domain": "pixel"}, {"position": {"minX": 326.0, "minY": 385.75, "maxX": 601.5, "maxY": 667.0}, "class_id": 41, "box_caption": "g 0.007", "scores": {"class_score": 0.007297515869140625}, "domain": "pixel"}, {"position": {"minX": 32.0625, "minY": 78.875, "maxX": 195.5, "maxY": 334.5}, "class_id": 19, "box_caption": "J 0.007", "scores": {"class_score": 0.007293701171875}, "domain": "pixel"}, {"position": {"minX": 32.0625, "minY": 78.875, "maxX": 195.5, "maxY": 334.5}, "class_id": 44, "box_caption": "q 0.007", "scores": {"class_score": 0.007282257080078125}, "domain": "pixel"}, {"position": {"minX": 326.0, "minY": 385.75, "maxX": 601.5, "maxY": 667.0}, "class_id": 21, "box_caption": "L 0.007", "scores": {"class_score": 0.0072784423828125}, "domain": "pixel"}, {"position": {"minX": 379.25, "minY": 439.75, "maxX": 678.0, "maxY": 671.5}, "class_id": 13, "box_caption": "D 0.007", "scores": {"class_score": 0.00727081298828125}, "domain": "pixel"}], "class_labels": {"0": "0", "1": "1", "2": "2", "3": "3", "4": "4", "5": "5", "6": "6", "7": "7", "8": "8", "9": "9", "10": "A", "11": "B", "12": "C", "13": "D", "14": "E", "15": "F", "16": "G", "17": "H", "18": "I", "19": "J", "20": "K", "21": "L", "22": "M", "23": "N", "24": "O", "25": "P", "26": "Q", "27": "R", "28": "S", "29": "T", "30": "U", "31": "V", "32": "W", "33": "X", "34": "Y", "35": "Z", "36": "a", "37": "b", "38": "d", "39": "e", "40": "f", "41": "g", "42": "h", "43": "n", "44": "q", "45": "r", "46": "t"}}