{"box_data": [{"position": {"minX": 299.75, "minY": 339.5, "maxX": 687.0, "maxY": 666.5}, "class_id": 34, "box_caption": "Y 0.013", "scores": {"class_score": 0.0133056640625}, "domain": "pixel"}, {"position": {"minX": 300.0, "minY": 336.75, "maxX": 687.5, "maxY": 664.0}, "class_id": 30, "box_caption": "U 0.013", "scores": {"class_score": 0.01322174072265625}, "domain": "pixel"}, {"position": {"minX": 300.0, "minY": 336.75, "maxX": 687.5, "maxY": 664.0}, "class_id": 28, "box_caption": "S 0.013", "scores": {"class_score": 0.01312255859375}, "domain": "pixel"}, {"position": {"minX": 299.75, "minY": 339.5, "maxX": 687.0, "maxY": 666.5}, "class_id": 35, "box_caption": "Z 0.013", "scores": {"class_score": 0.01300048828125}, "domain": "pixel"}, {"position": {"minX": 300.0, "minY": 336.75, "maxX": 687.5, "maxY": 664.0}, "class_id": 31, "box_caption": "V 0.013", "scores": {"class_score": 0.01267242431640625}, "domain": "pixel"}, {"position": {"minX": 299.75, "minY": 339.5, "maxX": 687.0, "maxY": 666.5}, "class_id": 36, "box_caption": "a 0.013", "scores": {"class_score": 0.01264190673828125}, "domain": "pixel"}, {"position": {"minX": 299.75, "minY": 339.5, "maxX": 687.0, "maxY": 666.5}, "class_id": 11, "box_caption": "B 0.013", "scores": {"class_score": 0.01256561279296875}, "domain": "pixel"}, {"position": {"minX": 300.0, "minY": 336.75, "maxX": 687.5, "maxY": 664.0}, "class_id": 14, "box_caption": "E 0.012", "scores": {"class_score": 0.01248931884765625}, "domain": "pixel"}, {"position": {"minX": 299.75, "minY": 339.5, "maxX": 687.0, "maxY": 666.5}, "class_id": 27, "box_caption": "R 0.012", "scores": {"class_score": 0.012451171875}, "domain": "pixel"}, {"position": {"minX": 300.0, "minY": 336.75, "maxX": 687.5, "maxY": 664.0}, "class_id": 39, "box_caption": "e 0.012", "scores": {"class_score": 0.01244354248046875}, "domain": "pixel"}, {"position": {"minX": 300.0, "minY": 336.75, "maxX": 687.5, "maxY": 664.0}, "class_id": 24, "box_caption": "O 0.012", "scores": {"class_score": 0.01239013671875}, "domain": "pixel"}, {"position": {"minX": 300.0, "minY": 336.75, "maxX": 687.5, "maxY": 664.0}, "class_id": 25, "box_caption": "P 0.012", "scores": {"class_score": 0.01236724853515625}, "domain": "pixel"}, {"position": {"minX": 299.75, "minY": 339.5, "maxX": 687.0, "maxY": 666.5}, "class_id": 45, "box_caption": "r 0.012", "scores": {"class_score": 0.01220703125}, "domain": "pixel"}, {"position": {"minX": 300.0, "minY": 336.75, "maxX": 687.5, "maxY": 664.0}, "class_id": 16, "box_caption": "G 0.012", "scores": {"class_score": 0.01219940185546875}, "domain": "pixel"}, {"position": {"minX": 322.75, "minY": 382.25, "maxX": 676.0, "maxY": 671.0}, "class_id": 2, "box_caption": "2 0.012", "scores": {"class_score": 0.0120697021484375}, "domain": "pixel"}, {"position": {"minX": 327.0, "minY": 382.0, "maxX": 670.0, "maxY": 673.0}, "class_id": 37, "box_caption": "b 0.012", "scores": {"class_score": 0.01203155517578125}, "domain": "pixel"}, {"position": {"minX": 324.5, "minY": 382.75, "maxX": 674.0, "maxY": 670.0}, "class_id": 38, "box_caption": "d 0.012", "scores": {"class_score": 0.011962890625}, "domain": "pixel"}, {"position": {"minX": 324.5, "minY": 382.75, "maxX": 674.0, "maxY": 670.0}, "class_id": 8, "box_caption": "8 0.012", "scores": {"class_score": 0.01189422607421875}, "domain": "pixel"}, {"position": {"minX": 324.5, "minY": 382.75, "maxX": 674.0, "maxY": 670.0}, "class_id": 10, "box_caption": "A 0.012", "scores": {"class_score": 0.01189422607421875}, "domain": "pixel"}, {"position": {"minX": 299.75, "minY": 339.5, "maxX": 687.0, "maxY": 666.5}, "class_id": 6, "box_caption": "6 0.012", "scores": {"class_score": 0.011871337890625}, "domain": "pixel"}, {"position": {"minX": 300.0, "minY": 336.75, "maxX": 687.5, "maxY": 664.0}, "class_id": 46, "box_caption": "t 0.012", "scores": {"class_score": 0.01183319091796875}, "domain": "pixel"}, {"position": {"minX": 300.0, "minY": 336.75, "maxX": 687.5, "maxY": 664.0}, "class_id": 26, "box_caption": "Q 0.012", "scores": {"class_score": 0.011810302734375}, "domain": "pixel"}, {"position": {"minX": 322.75, "minY": 382.25, "maxX": 676.0, "maxY": 671.0}, "class_id": 5, "box_caption": "5 0.012", "scores": {"class_score": 0.0117034912109375}, "domain": "pixel"}, {"position": {"minX": 324.5, "minY": 382.75, "maxX": 674.0, "maxY": 670.0}, "class_id": 33, "box_caption": "X 0.012", "scores": {"class_score": 0.0116424560546875}, "domain": "pixel"}, {"position": {"minX": 299.75, "minY": 339.5, "maxX": 687.0, "maxY": 666.5}, "class_id": 0, "box_caption": "0 0.012", "scores": {"class_score": 0.0115814208984375}, "domain": "pixel"}, {"position": {"minX": 322.75, "minY": 382.25, "maxX": 676.0, "maxY": 671.0}, "class_id": 3, "box_caption": "3 0.012", "scores": {"class_score": 0.01154327392578125}, "domain": "pixel"}, {"position": {"minX": 299.75, "minY": 339.5, "maxX": 687.0, "maxY": 666.5}, "class_id": 12, "box_caption": "C 0.012", "scores": {"class_score": 0.01151275634765625}, "domain": "pixel"}, {"position": {"minX": 300.0, "minY": 336.75, "maxX": 687.5, "maxY": 664.0}, "class_id": 44, "box_caption": "q 0.012", "scores": {"class_score": 0.011505126953125}, "domain": "pixel"}, {"position": {"minX": 327.0, "minY": 382.0, "maxX": 670.0, "maxY": 673.0}, "class_id": 17, "box_caption": "H 0.011", "scores": {"class_score": 0.01146697998046875}, "domain": "pixel"}, {"position": {"minX": 300.0, "minY": 336.75, "maxX": 687.5, "maxY": 664.0}, "class_id": 18, "box_caption": "I 0.011", "scores": {"class_score": 0.01137542724609375}, "domain": "pixel"}, {"position": {"minX": 324.5, "minY": 382.75, "maxX": 674.0, "maxY": 670.0}, "class_id": 22, "box_caption": "M 0.011", "scores": {"class_score": 0.01131439208984375}, "domain": "pixel"}, {"position": {"minX": 324.5, "minY": 382.75, "maxX": 674.0, "maxY": 670.0}, "class_id": 4, "box_caption": "4 0.011", "scores": {"class_score": 0.01129150390625}, "domain": "pixel"}, {"position": {"minX": 322.75, "minY": 382.25, "maxX": 676.0, "maxY": 671.0}, "class_id": 42, "box_caption": "h 0.011", "scores": {"class_score": 0.01128387451171875}, "domain": "pixel"}, {"position": {"minX": 324.5, "minY": 382.75, "maxX": 674.0, "maxY": 670.0}, "class_id": 15, "box_caption": "F 0.011", "scores": {"class_score": 0.0112762451171875}, "domain": "pixel"}, {"position": {"minX": 299.75, "minY": 339.5, "maxX": 687.0, "maxY": 666.5}, "class_id": 23, "box_caption": "N 0.011", "scores": {"class_score": 0.01126861572265625}, "domain": "pixel"}, {"position": {"minX": 299.75, "minY": 339.5, "maxX": 687.0, "maxY": 666.5}, "class_id": 19, "box_caption": "J 0.011", "scores": {"class_score": 0.01123046875}, "domain": "pixel"}, {"position": {"minX": 327.0, "minY": 382.0, "maxX": 670.0, "maxY": 673.0}, "class_id": 9, "box_caption": "9 0.011", "scores": {"class_score": 0.0112152099609375}, "domain": "pixel"}, {"position": {"minX": 322.75, "minY": 382.25, "maxX": 676.0, "maxY": 671.0}, "class_id": 41, "box_caption": "g 0.011", "scores": {"class_score": 0.011199951171875}, "domain": "pixel"}, {"position": {"minX": 300.0, "minY": 336.75, "maxX": 687.5, "maxY": 664.0}, "class_id": 7, "box_caption": "7 0.011", "scores": {"class_score": 0.01105499267578125}, "domain": "pixel"}, {"position": {"minX": 324.5, "minY": 382.75, "maxX": 674.0, "maxY": 670.0}, "class_id": 29, "box_caption": "T 0.011", "scores": {"class_score": 0.01099395751953125}, "domain": "pixel"}, {"position": {"minX": 327.0, "minY": 382.0, "maxX": 670.0, "maxY": 673.0}, "class_id": 40, "box_caption": "f 0.011", "scores": {"class_score": 0.010986328125}, "domain": "pixel"}, {"position": {"minX": 322.75, "minY": 382.25, "maxX": 676.0, "maxY": 671.0}, "class_id": 43, "box_caption": "n 0.011", "scores": {"class_score": 0.01090240478515625}, "domain": "pixel"}, {"position": {"minX": 130.5, "minY": 253.125, "maxX": 606.0, "maxY": 671.0}, "class_id": 25, "box_caption": "P 0.011", "scores": {"class_score": 0.01085662841796875}, "domain": "pixel"}, {"position": {"minX": 300.0, "minY": 336.75, "maxX": 687.5, "maxY": 664.0}, "class_id": 1, "box_caption": "1 0.011", "scores": {"class_score": 0.0108184814453125}, "domain": "pixel"}, {"position": {"minX": 324.5, "minY": 382.75, "maxX": 674.0, "maxY": 670.0}, "class_id": 20, "box_caption": "K 0.011", "scores": {"class_score": 0.01081085205078125}, "domain": "pixel"}, {"position": {"minX": 136.5, "minY": 188.375, "maxX": 600.5, "maxY": 680.0}, "class_id": 22, "box_caption": "M 0.011", "scores": {"class_score": 0.01081085205078125}, "domain": "pixel"}, {"position": {"minX": 149.5, "minY": 252.75, "maxX": 589.5, "maxY": 673.0}, "class_id": 31, "box_caption": "V 0.011", "scores": {"class_score": 0.01079559326171875}, "domain": "pixel"}, {"position": {"minX": 300.0, "minY": 336.75, "maxX": 687.5, "maxY": 664.0}, "class_id": 13, "box_caption": "D 0.011", "scores": {"class_score": 0.0107574462890625}, "domain": "pixel"}, {"position": {"minX": 322.75, "minY": 382.25, "maxX": 676.0, "maxY": 671.0}, "class_id": 21, "box_caption": "L 0.011", "scores": {"class_score": 0.0106964111328125}, "domain": "pixel"}, {"position": {"minX": 12.75, "minY": 40.375, "maxX": 345.75, "maxY": 506.0}, "class_id": 16, "box_caption": "G 0.011", "scores": {"class_score": 0.01067352294921875}, "domain": "pixel"}, {"position": {"minX": 300.0, "minY": 336.75, "maxX": 687.5, "maxY": 664.0}, "class_id": 32, "box_caption": "W 0.011", "scores": {"class_score": 0.0106201171875}, "domain": "pixel"}, {"position": {"minX": 130.5, "minY": 253.125, "maxX": 606.0, "maxY": 671.0}, "class_id": 35, "box_caption": "Z 0.010", "scores": {"class_score": 0.0100250244140625}, "domain": "pixel"}, {"position": {"minX": 149.5, "minY": 252.75, "maxX": 589.5, "maxY": 673.0}, "class_id": 19, "box_caption": "J 0.010", "scores": {"class_score": 0.00997161865234375}, "domain": "pixel"}, {"position": {"minX": 2.4375, "minY": -8.875, "maxX": 217.75, "maxY": 367.5}, "class_id": 0, "box_caption": "0 0.010", "scores": {"class_score": 0.00995635986328125}, "domain": "pixel"}, {"position": {"minX": 350.5, "minY": 431.0, "maxX": 645.5, "maxY": 671.0}, "class_id": 27, "box_caption": "R 0.010", "scores": {"class_score": 0.00982666015625}, "domain": "pixel"}, {"position": {"minX": 3.25, "minY": -9.0, "maxX": 216.125, "maxY": 368.0}, "class_id": 33, "box_caption": "X 0.010", "scores": {"class_score": 0.009765625}, "domain": "pixel"}, {"position": {"minX": 125.125, "minY": 189.375, "maxX": 610.0, "maxY": 675.0}, "class_id": 1, "box_caption": "1 0.010", "scores": {"class_score": 0.00969696044921875}, "domain": "pixel"}, {"position": {"minX": 2.4375, "minY": -8.875, "maxX": 217.75, "maxY": 367.5}, "class_id": 6, "box_caption": "6 0.010", "scores": {"class_score": 0.00969696044921875}, "domain": "pixel"}, {"position": {"minX": 136.5, "minY": 188.375, "maxX": 600.5, "maxY": 680.0}, "class_id": 39, "box_caption": "e 0.010", "scores": {"class_score": 0.00969696044921875}, "domain": "pixel"}, {"position": {"minX": 12.75, "minY": 40.375, "maxX": 345.75, "maxY": 506.0}, "class_id": 14, "box_caption": "E 0.010", "scores": {"class_score": 0.009674072265625}, "domain": "pixel"}, {"position": {"minX": 125.125, "minY": 189.375, "maxX": 610.0, "maxY": 675.0}, "class_id": 33, "box_caption": "X 0.010", "scores": {"class_score": 0.0096282958984375}, "domain": "pixel"}, {"position": {"minX": 350.5, "minY": 431.0, "maxX": 645.5, "maxY": 671.0}, "class_id": 26, "box_caption": "Q 0.010", "scores": {"class_score": 0.0096282958984375}, "domain": "pixel"}, {"position": {"minX": 354.0, "minY": 434.0, "maxX": 643.5, "maxY": 671.0}, "class_id": 35, "box_caption": "Z 0.010", "scores": {"class_score": 0.00959014892578125}, "domain": "pixel"}, {"position": {"minX": 350.5, "minY": 431.0, "maxX": 645.5, "maxY": 671.0}, "class_id": 36, "box_caption": "a 0.010", "scores": {"class_score": 0.00957489013671875}, "domain": "pixel"}, {"position": {"minX": 350.5, "minY": 431.0, "maxX": 645.5, "maxY": 671.0}, "class_id": 46, "box_caption": "t 0.010", "scores": {"class_score": 0.00957489013671875}, "domain": "pixel"}, {"position": {"minX": 12.75, "minY": 40.375, "maxX": 345.75, "maxY": 506.0}, "class_id": 17, "box_caption": "H 0.010", "scores": {"class_score": 0.0095367431640625}, "domain": "pixel"}, {"position": {"minX": 3.25, "minY": -9.0, "maxX": 216.125, "maxY": 368.0}, "class_id": 5, "box_caption": "5 0.010", "scores": {"class_score": 0.00951385498046875}, "domain": "pixel"}, {"position": {"minX": 3.25, "minY": -9.0, "maxX": 216.125, "maxY": 368.0}, "class_id": 20, "box_caption": "K 0.009", "scores": {"class_score": 0.00948333740234375}, "domain": "pixel"}, {"position": {"minX": 354.0, "minY": 434.0, "maxX": 643.5, "maxY": 671.0}, "class_id": 30, "box_caption": "U 0.009", "scores": {"class_score": 0.0094757080078125}, "domain": "pixel"}, {"position": {"minX": 350.5, "minY": 431.0, "maxX": 645.5, "maxY": 671.0}, "class_id": 34, "box_caption": "Y 0.009", "scores": {"class_score": 0.0094757080078125}, "domain": "pixel"}, {"position": {"minX": 12.75, "minY": 40.375, "maxX": 345.75, "maxY": 506.0}, "class_id": 46, "box_caption": "t 0.009", "scores": {"class_score": 0.00946044921875}, "domain": "pixel"}, {"position": {"minX": 354.0, "minY": 434.0, "maxX": 643.5, "maxY": 671.0}, "class_id": 31, "box_caption": "V 0.009", "scores": {"class_score": 0.00942230224609375}, "domain": "pixel"}, {"position": {"minX": 2.4375, "minY": -8.875, "maxX": 217.75, "maxY": 367.5}, "class_id": 14, "box_caption": "E 0.009", "scores": {"class_score": 0.00942230224609375}, "domain": "pixel"}, {"position": {"minX": 130.5, "minY": 253.125, "maxX": 606.0, "maxY": 671.0}, "class_id": 36, "box_caption": "a 0.009", "scores": {"class_score": 0.0094146728515625}, "domain": "pixel"}, {"position": {"minX": 12.75, "minY": 40.375, "maxX": 345.75, "maxY": 506.0}, "class_id": 31, "box_caption": "V 0.009", "scores": {"class_score": 0.00939178466796875}, "domain": "pixel"}, {"position": {"minX": 136.5, "minY": 188.375, "maxX": 600.5, "maxY": 680.0}, "class_id": 30, "box_caption": "U 0.009", "scores": {"class_score": 0.00939178466796875}, "domain": "pixel"}, {"position": {"minX": 125.125, "minY": 189.375, "maxX": 610.0, "maxY": 675.0}, "class_id": 9, "box_caption": "9 0.009", "scores": {"class_score": 0.0093841552734375}, "domain": "pixel"}, {"position": {"minX": 2.4375, "minY": -8.875, "maxX": 217.75, "maxY": 367.5}, "class_id": 17, "box_caption": "H 0.009", "scores": {"class_score": 0.009368896484375}, "domain": "pixel"}, {"position": {"minX": 136.5, "minY": 188.375, "maxX": 600.5, "maxY": 680.0}, "class_id": 40, "box_caption": "f 0.009", "scores": {"class_score": 0.00933074951171875}, "domain": "pixel"}, {"position": {"minX": 350.5, "minY": 431.0, "maxX": 645.5, "maxY": 671.0}, "class_id": 39, "box_caption": "e 0.009", "scores": {"class_score": 0.009307861328125}, "domain": "pixel"}, {"position": {"minX": 2.4375, "minY": -8.875, "maxX": 217.75, "maxY": 367.5}, "class_id": 26, "box_caption": "Q 0.009", "scores": {"class_score": 0.00930023193359375}, "domain": "pixel"}, {"position": {"minX": 149.5, "minY": 252.75, "maxX": 589.5, "maxY": 673.0}, "class_id": 14, "box_caption": "E 0.009", "scores": {"class_score": 0.00928497314453125}, "domain": "pixel"}, {"position": {"minX": 125.125, "minY": 189.375, "maxX": 610.0, "maxY": 675.0}, "class_id": 3, "box_caption": "3 0.009", "scores": {"class_score": 0.00927734375}, "domain": "pixel"}, {"position": {"minX": 149.5, "minY": 252.75, "maxX": 589.5, "maxY": 673.0}, "class_id": 43, "box_caption": "n 0.009", "scores": {"class_score": 0.00926971435546875}, "domain": "pixel"}, {"position": {"minX": 3.25, "minY": -9.0, "maxX": 216.125, "maxY": 368.0}, "class_id": 3, "box_caption": "3 0.009", "scores": {"class_score": 0.00925445556640625}, "domain": "pixel"}, {"position": {"minX": 3.25, "minY": -9.0, "maxX": 216.125, "maxY": 368.0}, "class_id": 39, "box_caption": "e 0.009", "scores": {"class_score": 0.00925445556640625}, "domain": "pixel"}, {"position": {"minX": 12.75, "minY": 40.375, "maxX": 345.75, "maxY": 506.0}, "class_id": 27, "box_caption": "R 0.009", "scores": {"class_score": 0.00925445556640625}, "domain": "pixel"}, {"position": {"minX": 33.5, "minY": 106.0, "maxX": 454.5, "maxY": 626.5}, "class_id": 19, "box_caption": "J 0.009", "scores": {"class_score": 0.009246826171875}, "domain": "pixel"}, {"position": {"minX": 125.125, "minY": 189.375, "maxX": 610.0, "maxY": 675.0}, "class_id": 15, "box_caption": "F 0.009", "scores": {"class_score": 0.0092315673828125}, "domain": "pixel"}, {"position": {"minX": 12.75, "minY": 40.375, "maxX": 345.75, "maxY": 506.0}, "class_id": 43, "box_caption": "n 0.009", "scores": {"class_score": 0.00922393798828125}, "domain": "pixel"}, {"position": {"minX": 149.5, "minY": 252.75, "maxX": 589.5, "maxY": 673.0}, "class_id": 38, "box_caption": "d 0.009", "scores": {"class_score": 0.00922393798828125}, "domain": "pixel"}, {"position": {"minX": 3.25, "minY": -9.0, "maxX": 216.125, "maxY": 368.0}, "class_id": 13, "box_caption": "D 0.009", "scores": {"class_score": 0.00921630859375}, "domain": "pixel"}, {"position": {"minX": 354.0, "minY": 434.0, "maxX": 643.5, "maxY": 671.0}, "class_id": 32, "box_caption": "W 0.009", "scores": {"class_score": 0.00920867919921875}, "domain": "pixel"}, {"position": {"minX": 12.75, "minY": 40.375, "maxX": 345.75, "maxY": 506.0}, "class_id": 22, "box_caption": "M 0.009", "scores": {"class_score": 0.0092010498046875}, "domain": "pixel"}, {"position": {"minX": 149.5, "minY": 252.75, "maxX": 589.5, "maxY": 673.0}, "class_id": 17, "box_caption": "H 0.009", "scores": {"class_score": 0.0092010498046875}, "domain": "pixel"}, {"position": {"minX": 354.0, "minY": 434.0, "maxX": 643.5, "maxY": 671.0}, "class_id": 25, "box_caption": "P 0.009", "scores": {"class_score": 0.009185791015625}, "domain": "pixel"}, {"position": {"minX": 12.75, "minY": 40.375, "maxX": 345.75, "maxY": 506.0}, "class_id": 0, "box_caption": "0 0.009", "scores": {"class_score": 0.009185791015625}, "domain": "pixel"}, {"position": {"minX": 350.5, "minY": 431.0, "maxX": 645.5, "maxY": 671.0}, "class_id": 23, "box_caption": "N 0.009", "scores": {"class_score": 0.00917816162109375}, "domain": "pixel"}, {"position": {"minX": 7.375, "minY": 39.625, "maxX": 349.0, "maxY": 506.5}, "class_id": 33, "box_caption": "X 0.009", "scores": {"class_score": 0.0091705322265625}, "domain": "pixel"}, {"position": {"minX": 136.5, "minY": 188.375, "maxX": 600.5, "maxY": 680.0}, "class_id": 34, "box_caption": "Y 0.009", "scores": {"class_score": 0.00916290283203125}, "domain": "pixel"}, {"position": {"minX": 3.25, "minY": -9.0, "maxX": 216.125, "maxY": 368.0}, "class_id": 30, "box_caption": "U 0.009", "scores": {"class_score": 0.00914764404296875}, "domain": "pixel"}, {"position": {"minX": 130.5, "minY": 253.125, "maxX": 606.0, "maxY": 671.0}, "class_id": 41, "box_caption": "g 0.009", "scores": {"class_score": 0.00913238525390625}, "domain": "pixel"}, {"position": {"minX": 12.75, "minY": 40.375, "maxX": 345.75, "maxY": 506.0}, "class_id": 26, "box_caption": "Q 0.009", "scores": {"class_score": 0.00913238525390625}, "domain": "pixel"}, {"position": {"minX": 354.0, "minY": 434.0, "maxX": 643.5, "maxY": 671.0}, "class_id": 14, "box_caption": "E 0.009", "scores": {"class_score": 0.00910186767578125}, "domain": "pixel"}, {"position": {"minX": 2.4375, "minY": -8.875, "maxX": 217.75, "maxY": 367.5}, "class_id": 46, "box_caption": "t 0.009", "scores": {"class_score": 0.00910186767578125}, "domain": "pixel"}, {"position": {"minX": 12.75, "minY": 40.375, "maxX": 345.75, "maxY": 506.0}, "class_id": 12, "box_caption": "C 0.009", "scores": {"class_score": 0.00909423828125}, "domain": "pixel"}, {"position": {"minX": 3.25, "minY": -9.0, "maxX": 216.125, "maxY": 368.0}, "class_id": 35, "box_caption": "Z 0.009", "scores": {"class_score": 0.00905609130859375}, "domain": "pixel"}, {"position": {"minX": 136.5, "minY": 188.375, "maxX": 600.5, "maxY": 680.0}, "class_id": 10, "box_caption": "A 0.009", "scores": {"class_score": 0.00904083251953125}, "domain": "pixel"}, {"position": {"minX": 3.25, "minY": -9.0, "maxX": 216.125, "maxY": 368.0}, "class_id": 11, "box_caption": "B 0.009", "scores": {"class_score": 0.00902557373046875}, "domain": "pixel"}, {"position": {"minX": 3.25, "minY": -9.0, "maxX": 216.125, "maxY": 368.0}, "class_id": 34, "box_caption": "Y 0.009", "scores": {"class_score": 0.00902557373046875}, "domain": "pixel"}, {"position": {"minX": 125.125, "minY": 189.375, "maxX": 610.0, "maxY": 675.0}, "class_id": 28, "box_caption": "S 0.009", "scores": {"class_score": 0.0090179443359375}, "domain": "pixel"}, {"position": {"minX": 2.4375, "minY": -8.875, "maxX": 217.75, "maxY": 367.5}, "class_id": 19, "box_caption": "J 0.009", "scores": {"class_score": 0.009002685546875}, "domain": "pixel"}, {"position": {"minX": 136.5, "minY": 188.375, "maxX": 600.5, "maxY": 680.0}, "class_id": 16, "box_caption": "G 0.009", "scores": {"class_score": 0.009002685546875}, "domain": "pixel"}, {"position": {"minX": 350.5, "minY": 431.0, "maxX": 645.5, "maxY": 671.0}, "class_id": 12, "box_caption": "C 0.009", "scores": {"class_score": 0.0089874267578125}, "domain": "pixel"}, {"position": {"minX": 2.4375, "minY": -8.875, "maxX": 217.75, "maxY": 367.5}, "class_id": 25, "box_caption": "P 0.009", "scores": {"class_score": 0.00897979736328125}, "domain": "pixel"}, {"position": {"minX": 3.25, "minY": -9.0, "maxX": 216.125, "maxY": 368.0}, "class_id": 15, "box_caption": "F 0.009", "scores": {"class_score": 0.00897216796875}, "domain": "pixel"}, {"position": {"minX": 354.0, "minY": 434.0, "maxX": 643.5, "maxY": 671.0}, "class_id": 16, "box_caption": "G 0.009", "scores": {"class_score": 0.00896453857421875}, "domain": "pixel"}, {"position": {"minX": 354.0, "minY": 434.0, "maxX": 643.5, "maxY": 671.0}, "class_id": 44, "box_caption": "q 0.009", "scores": {"class_score": 0.00896453857421875}, "domain": "pixel"}, {"position": {"minX": 350.5, "minY": 431.0, "maxX": 645.5, "maxY": 671.0}, "class_id": 11, "box_caption": "B 0.009", "scores": {"class_score": 0.00896453857421875}, "domain": "pixel"}, {"position": {"minX": 350.5, "minY": 431.0, "maxX": 645.5, "maxY": 671.0}, "class_id": 19, "box_caption": "J 0.009", "scores": {"class_score": 0.0089569091796875}, "domain": "pixel"}, {"position": {"minX": 350.5, "minY": 431.0, "maxX": 645.5, "maxY": 671.0}, "class_id": 24, "box_caption": "O 0.009", "scores": {"class_score": 0.0089569091796875}, "domain": "pixel"}, {"position": {"minX": 353.5, "minY": 432.75, "maxX": 642.0, "maxY": 672.5}, "class_id": 0, "box_caption": "0 0.009", "scores": {"class_score": 0.00891876220703125}, "domain": "pixel"}, {"position": {"minX": 2.4375, "minY": -8.875, "maxX": 217.75, "maxY": 367.5}, "class_id": 22, "box_caption": "M 0.009", "scores": {"class_score": 0.00891876220703125}, "domain": "pixel"}, {"position": {"minX": 12.75, "minY": 40.375, "maxX": 345.75, "maxY": 506.0}, "class_id": 24, "box_caption": "O 0.009", "scores": {"class_score": 0.00891876220703125}, "domain": "pixel"}, {"position": {"minX": 12.75, "minY": 40.375, "maxX": 345.75, "maxY": 506.0}, "class_id": 30, "box_caption": "U 0.009", "scores": {"class_score": 0.0089111328125}, "domain": "pixel"}, {"position": {"minX": 3.25, "minY": -9.0, "maxX": 216.125, "maxY": 368.0}, "class_id": 8, "box_caption": "8 0.009", "scores": {"class_score": 0.00890350341796875}, "domain": "pixel"}, {"position": {"minX": 3.25, "minY": -9.0, "maxX": 216.125, "maxY": 368.0}, "class_id": 27, "box_caption": "R 0.009", "scores": {"class_score": 0.00890350341796875}, "domain": "pixel"}, {"position": {"minX": 3.25, "minY": -9.0, "maxX": 216.125, "maxY": 368.0}, "class_id": 9, "box_caption": "9 0.009", "scores": {"class_score": 0.00888824462890625}, "domain": "pixel"}, {"position": {"minX": 2.4375, "minY": -8.875, "maxX": 217.75, "maxY": 367.5}, "class_id": 32, "box_caption": "W 0.009", "scores": {"class_score": 0.008880615234375}, "domain": "pixel"}, {"position": {"minX": 12.75, "minY": 40.375, "maxX": 345.75, "maxY": 506.0}, "class_id": 25, "box_caption": "P 0.009", "scores": {"class_score": 0.00887298583984375}, "domain": "pixel"}, {"position": {"minX": 149.5, "minY": 252.75, "maxX": 589.5, "maxY": 673.0}, "class_id": 6, "box_caption": "6 0.009", "scores": {"class_score": 0.00887298583984375}, "domain": "pixel"}, {"position": {"minX": 3.25, "minY": -9.0, "maxX": 216.125, "maxY": 368.0}, "class_id": 43, "box_caption": "n 0.009", "scores": {"class_score": 0.0088653564453125}, "domain": "pixel"}, {"position": {"minX": 12.75, "minY": 40.375, "maxX": 345.75, "maxY": 506.0}, "class_id": 13, "box_caption": "D 0.009", "scores": {"class_score": 0.008819580078125}, "domain": "pixel"}, {"position": {"minX": 27.25, "minY": 105.5, "maxX": 457.25, "maxY": 626.0}, "class_id": 25, "box_caption": "P 0.009", "scores": {"class_score": 0.00881195068359375}, "domain": "pixel"}, {"position": {"minX": 2.4375, "minY": -8.875, "maxX": 217.75, "maxY": 367.5}, "class_id": 37, "box_caption": "b 0.009", "scores": {"class_score": 0.00881195068359375}, "domain": "pixel"}, {"position": {"minX": 149.5, "minY": 252.75, "maxX": 589.5, "maxY": 673.0}, "class_id": 7, "box_caption": "7 0.009", "scores": {"class_score": 0.0088043212890625}, "domain": "pixel"}, {"position": {"minX": 130.5, "minY": 253.125, "maxX": 606.0, "maxY": 671.0}, "class_id": 44, "box_caption": "q 0.009", "scores": {"class_score": 0.00879669189453125}, "domain": "pixel"}, {"position": {"minX": 354.0, "minY": 434.0, "maxX": 643.5, "maxY": 671.0}, "class_id": 28, "box_caption": "S 0.009", "scores": {"class_score": 0.00879669189453125}, "domain": "pixel"}, {"position": {"minX": 350.5, "minY": 431.0, "maxX": 645.5, "maxY": 671.0}, "class_id": 6, "box_caption": "6 0.009", "scores": {"class_score": 0.00879669189453125}, "domain": "pixel"}, {"position": {"minX": 12.75, "minY": 40.375, "maxX": 345.75, "maxY": 506.0}, "class_id": 3, "box_caption": "3 0.009", "scores": {"class_score": 0.0087890625}, "domain": "pixel"}, {"position": {"minX": 12.75, "minY": 40.375, "maxX": 345.75, "maxY": 506.0}, "class_id": 38, "box_caption": "d 0.009", "scores": {"class_score": 0.0087890625}, "domain": "pixel"}, {"position": {"minX": 12.75, "minY": 40.375, "maxX": 345.75, "maxY": 506.0}, "class_id": 41, "box_caption": "g 0.009", "scores": {"class_score": 0.0087890625}, "domain": "pixel"}, {"position": {"minX": 12.75, "minY": 40.375, "maxX": 345.75, "maxY": 506.0}, "class_id": 45, "box_caption": "r 0.009", "scores": {"class_score": 0.0087890625}, "domain": "pixel"}, {"position": {"minX": 3.25, "minY": -9.0, "maxX": 216.125, "maxY": 368.0}, "class_id": 23, "box_caption": "N 0.009", "scores": {"class_score": 0.0087738037109375}, "domain": "pixel"}, {"position": {"minX": 130.5, "minY": 253.125, "maxX": 606.0, "maxY": 671.0}, "class_id": 46, "box_caption": "t 0.009", "scores": {"class_score": 0.0087738037109375}, "domain": "pixel"}, {"position": {"minX": 2.4375, "minY": -8.875, "maxX": 217.75, "maxY": 367.5}, "class_id": 42, "box_caption": "h 0.009", "scores": {"class_score": 0.0087738037109375}, "domain": "pixel"}, {"position": {"minX": 353.5, "minY": 432.75, "maxX": 642.0, "maxY": 672.5}, "class_id": 18, "box_caption": "I 0.009", "scores": {"class_score": 0.00876617431640625}, "domain": "pixel"}, {"position": {"minX": 2.4375, "minY": -8.875, "maxX": 217.75, "maxY": 367.5}, "class_id": 7, "box_caption": "7 0.009", "scores": {"class_score": 0.00876617431640625}, "domain": "pixel"}, {"position": {"minX": 2.4375, "minY": -8.875, "maxX": 217.75, "maxY": 367.5}, "class_id": 16, "box_caption": "G 0.009", "scores": {"class_score": 0.00876617431640625}, "domain": "pixel"}, {"position": {"minX": 3.25, "minY": -9.0, "maxX": 216.125, "maxY": 368.0}, "class_id": 36, "box_caption": "a 0.009", "scores": {"class_score": 0.00875091552734375}, "domain": "pixel"}, {"position": {"minX": 130.5, "minY": 253.125, "maxX": 606.0, "maxY": 671.0}, "class_id": 37, "box_caption": "b 0.009", "scores": {"class_score": 0.0087432861328125}, "domain": "pixel"}, {"position": {"minX": 12.75, "minY": 40.375, "maxX": 345.75, "maxY": 506.0}, "class_id": 8, "box_caption": "8 0.009", "scores": {"class_score": 0.00873565673828125}, "domain": "pixel"}, {"position": {"minX": 3.25, "minY": -9.0, "maxX": 216.125, "maxY": 368.0}, "class_id": 4, "box_caption": "4 0.009", "scores": {"class_score": 0.00870513916015625}, "domain": "pixel"}, {"position": {"minX": 3.25, "minY": -9.0, "maxX": 216.125, "maxY": 368.0}, "class_id": 29, "box_caption": "T 0.009", "scores": {"class_score": 0.00870513916015625}, "domain": "pixel"}, {"position": {"minX": 2.4375, "minY": -8.875, "maxX": 217.75, "maxY": 367.5}, "class_id": 31, "box_caption": "V 0.009", "scores": {"class_score": 0.008697509765625}, "domain": "pixel"}, {"position": {"minX": 7.375, "minY": 39.625, "maxX": 349.0, "maxY": 506.5}, "class_id": 39, "box_caption": "e 0.009", "scores": {"class_score": 0.00868988037109375}, "domain": "pixel"}, {"position": {"minX": 130.5, "minY": 253.125, "maxX": 606.0, "maxY": 671.0}, "class_id": 21, "box_caption": "L 0.009", "scores": {"class_score": 0.00868988037109375}, "domain": "pixel"}, {"position": {"minX": 2.4375, "minY": -8.875, "maxX": 217.75, "maxY": 367.5}, "class_id": 24, "box_caption": "O 0.009", "scores": {"class_score": 0.0086822509765625}, "domain": "pixel"}, {"position": {"minX": 3.25, "minY": -9.0, "maxX": 216.125, "maxY": 368.0}, "class_id": 41, "box_caption": "g 0.009", "scores": {"class_score": 0.00867462158203125}, "domain": "pixel"}, {"position": {"minX": 12.75, "minY": 40.375, "maxX": 345.75, "maxY": 506.0}, "class_id": 32, "box_caption": "W 0.009", "scores": {"class_score": 0.0086669921875}, "domain": "pixel"}, {"position": {"minX": 2.4375, "minY": -8.875, "maxX": 217.75, "maxY": 367.5}, "class_id": 40, "box_caption": "f 0.009", "scores": {"class_score": 0.00865936279296875}, "domain": "pixel"}, {"position": {"minX": 3.25, "minY": -9.0, "maxX": 216.125, "maxY": 368.0}, "class_id": 38, "box_caption": "d 0.009", "scores": {"class_score": 0.008636474609375}, "domain": "pixel"}, {"position": {"minX": 130.5, "minY": 253.125, "maxX": 606.0, "maxY": 671.0}, "class_id": 26, "box_caption": "Q 0.009", "scores": {"class_score": 0.008636474609375}, "domain": "pixel"}, {"position": {"minX": 12.75, "minY": 40.375, "maxX": 345.75, "maxY": 506.0}, "class_id": 10, "box_caption": "A 0.009", "scores": {"class_score": 0.008636474609375}, "domain": "pixel"}, {"position": {"minX": 3.25, "minY": -9.0, "maxX": 216.125, "maxY": 368.0}, "class_id": 10, "box_caption": "A 0.009", "scores": {"class_score": 0.0086212158203125}, "domain": "pixel"}, {"position": {"minX": 130.5, "minY": 253.125, "maxX": 606.0, "maxY": 671.0}, "class_id": 45, "box_caption": "r 0.009", "scores": {"class_score": 0.0086212158203125}, "domain": "pixel"}, {"position": {"minX": 12.75, "minY": 40.375, "maxX": 345.75, "maxY": 506.0}, "class_id": 6, "box_caption": "6 0.009", "scores": {"class_score": 0.0086212158203125}, "domain": "pixel"}, {"position": {"minX": 125.125, "minY": 189.375, "maxX": 610.0, "maxY": 675.0}, "class_id": 24, "box_caption": "O 0.009", "scores": {"class_score": 0.00858306884765625}, "domain": "pixel"}, {"position": {"minX": 7.375, "minY": 39.625, "maxX": 349.0, "maxY": 506.5}, "class_id": 19, "box_caption": "J 0.009", "scores": {"class_score": 0.008575439453125}, "domain": "pixel"}, {"position": {"minX": 354.0, "minY": 434.0, "maxX": 643.5, "maxY": 671.0}, "class_id": 7, "box_caption": "7 0.009", "scores": {"class_score": 0.008575439453125}, "domain": "pixel"}, {"position": {"minX": 125.125, "minY": 189.375, "maxX": 610.0, "maxY": 675.0}, "class_id": 20, "box_caption": "K 0.009", "scores": {"class_score": 0.00856781005859375}, "domain": "pixel"}, {"position": {"minX": 350.5, "minY": 431.0, "maxX": 645.5, "maxY": 671.0}, "class_id": 13, "box_caption": "D 0.009", "scores": {"class_score": 0.00856781005859375}, "domain": "pixel"}, {"position": {"minX": 12.75, "minY": 40.375, "maxX": 345.75, "maxY": 506.0}, "class_id": 15, "box_caption": "F 0.009", "scores": {"class_score": 0.0085601806640625}, "domain": "pixel"}, {"position": {"minX": 12.75, "minY": 40.375, "maxX": 345.75, "maxY": 506.0}, "class_id": 34, "box_caption": "Y 0.009", "scores": {"class_score": 0.0085601806640625}, "domain": "pixel"}, {"position": {"minX": 12.75, "minY": 40.375, "maxX": 345.75, "maxY": 506.0}, "class_id": 40, "box_caption": "f 0.009", "scores": {"class_score": 0.0085601806640625}, "domain": "pixel"}, {"position": {"minX": 3.25, "minY": -9.0, "maxX": 216.125, "maxY": 368.0}, "class_id": 2, "box_caption": "2 0.009", "scores": {"class_score": 0.00853729248046875}, "domain": "pixel"}, {"position": {"minX": 33.5, "minY": 106.0, "maxX": 454.5, "maxY": 626.5}, "class_id": 16, "box_caption": "G 0.009", "scores": {"class_score": 0.00853729248046875}, "domain": "pixel"}, {"position": {"minX": 7.375, "minY": 39.625, "maxX": 349.0, "maxY": 506.5}, "class_id": 5, "box_caption": "5 0.009", "scores": {"class_score": 0.008514404296875}, "domain": "pixel"}, {"position": {"minX": 3.25, "minY": -9.0, "maxX": 216.125, "maxY": 368.0}, "class_id": 21, "box_caption": "L 0.009", "scores": {"class_score": 0.00850677490234375}, "domain": "pixel"}, {"position": {"minX": 33.5, "minY": 106.0, "maxX": 454.5, "maxY": 626.5}, "class_id": 22, "box_caption": "M 0.009", "scores": {"class_score": 0.00850677490234375}, "domain": "pixel"}, {"position": {"minX": 33.5, "minY": 106.0, "maxX": 454.5, "maxY": 626.5}, "class_id": 31, "box_caption": "V 0.009", "scores": {"class_score": 0.00850677490234375}, "domain": "pixel"}, {"position": {"minX": 368.75, "minY": 444.0, "maxX": 570.5, "maxY": 670.0}, "class_id": 2, "box_caption": "2 0.008", "scores": {"class_score": 0.0084991455078125}, "domain": "pixel"}, {"position": {"minX": 7.375, "minY": 39.625, "maxX": 349.0, "maxY": 506.5}, "class_id": 35, "box_caption": "Z 0.008", "scores": {"class_score": 0.00848388671875}, "domain": "pixel"}, {"position": {"minX": 136.5, "minY": 188.375, "maxX": 600.5, "maxY": 680.0}, "class_id": 2, "box_caption": "2 0.008", "scores": {"class_score": 0.00848388671875}, "domain": "pixel"}, {"position": {"minX": 136.5, "minY": 188.375, "maxX": 600.5, "maxY": 680.0}, "class_id": 5, "box_caption": "5 0.008", "scores": {"class_score": 0.00848388671875}, "domain": "pixel"}, {"position": {"minX": 2.4375, "minY": -8.875, "maxX": 217.75, "maxY": 367.5}, "class_id": 28, "box_caption": "S 0.008", "scores": {"class_score": 0.0084686279296875}, "domain": "pixel"}, {"position": {"minX": 12.75, "minY": 40.375, "maxX": 345.75, "maxY": 506.0}, "class_id": 1, "box_caption": "1 0.008", "scores": {"class_score": 0.00846099853515625}, "domain": "pixel"}, {"position": {"minX": 12.75, "minY": 40.375, "maxX": 345.75, "maxY": 506.0}, "class_id": 11, "box_caption": "B 0.008", "scores": {"class_score": 0.00846099853515625}, "domain": "pixel"}, {"position": {"minX": 350.5, "minY": 431.0, "maxX": 645.5, "maxY": 671.0}, "class_id": 1, "box_caption": "1 0.008", "scores": {"class_score": 0.008453369140625}, "domain": "pixel"}, {"position": {"minX": 7.375, "minY": 39.625, "maxX": 349.0, "maxY": 506.5}, "class_id": 20, "box_caption": "K 0.008", "scores": {"class_score": 0.00844573974609375}, "domain": "pixel"}, {"position": {"minX": 136.5, "minY": 188.375, "maxX": 600.5, "maxY": 680.0}, "class_id": 32, "box_caption": "W 0.008", "scores": {"class_score": 0.0084381103515625}, "domain": "pixel"}, {"position": {"minX": 2.4375, "minY": -8.875, "maxX": 217.75, "maxY": 367.5}, "class_id": 12, "box_caption": "C 0.008", "scores": {"class_score": 0.0084228515625}, "domain": "pixel"}, {"position": {"minX": 12.75, "minY": 40.375, "maxX": 345.75, "maxY": 506.0}, "class_id": 7, "box_caption": "7 0.008", "scores": {"class_score": 0.0084228515625}, "domain": "pixel"}, {"position": {"minX": 3.25, "minY": -9.0, "maxX": 216.125, "maxY": 368.0}, "class_id": 45, "box_caption": "r 0.008", "scores": {"class_score": 0.0084075927734375}, "domain": "pixel"}, {"position": {"minX": 12.75, "minY": 40.375, "maxX": 345.75, "maxY": 506.0}, "class_id": 23, "box_caption": "N 0.008", "scores": {"class_score": 0.008392333984375}, "domain": "pixel"}, {"position": {"minX": 12.75, "minY": 40.375, "maxX": 345.75, "maxY": 506.0}, "class_id": 28, "box_caption": "S 0.008", "scores": {"class_score": 0.008392333984375}, "domain": "pixel"}, {"position": {"minX": 130.5, "minY": 253.125, "maxX": 606.0, "maxY": 671.0}, "class_id": 27, "box_caption": "R 0.008", "scores": {"class_score": 0.0083770751953125}, "domain": "pixel"}, {"position": {"minX": 12.75, "minY": 40.375, "maxX": 345.75, "maxY": 506.0}, "class_id": 42, "box_caption": "h 0.008", "scores": {"class_score": 0.0083770751953125}, "domain": "pixel"}, {"position": {"minX": 136.5, "minY": 188.375, "maxX": 600.5, "maxY": 680.0}, "class_id": 11, "box_caption": "B 0.008", "scores": {"class_score": 0.00836944580078125}, "domain": "pixel"}, {"position": {"minX": 7.375, "minY": 39.625, "maxX": 349.0, "maxY": 506.5}, "class_id": 18, "box_caption": "I 0.008", "scores": {"class_score": 0.00835418701171875}, "domain": "pixel"}, {"position": {"minX": 12.75, "minY": 40.375, "maxX": 345.75, "maxY": 506.0}, "class_id": 4, "box_caption": "4 0.008", "scores": {"class_score": 0.008331298828125}, "domain": "pixel"}, {"position": {"minX": 27.25, "minY": 105.5, "maxX": 457.25, "maxY": 626.0}, "class_id": 36, "box_caption": "a 0.008", "scores": {"class_score": 0.00830841064453125}, "domain": "pixel"}, {"position": {"minX": 7.375, "minY": 39.625, "maxX": 349.0, "maxY": 506.5}, "class_id": 36, "box_caption": "a 0.008", "scores": {"class_score": 0.00830078125}, "domain": "pixel"}, {"position": {"minX": 12.75, "minY": 40.375, "maxX": 345.75, "maxY": 506.0}, "class_id": 9, "box_caption": "9 0.008", "scores": {"class_score": 0.00829315185546875}, "domain": "pixel"}, {"position": {"minX": 130.5, "minY": 253.125, "maxX": 606.0, "maxY": 671.0}, "class_id": 23, "box_caption": "N 0.008", "scores": {"class_score": 0.0082855224609375}, "domain": "pixel"}, {"position": {"minX": 353.5, "minY": 432.75, "maxX": 642.0, "maxY": 672.5}, "class_id": 45, "box_caption": "r 0.008", "scores": {"class_score": 0.00827789306640625}, "domain": "pixel"}, {"position": {"minX": 2.4375, "minY": -8.875, "maxX": 217.75, "maxY": 367.5}, "class_id": 18, "box_caption": "I 0.008", "scores": {"class_score": 0.00827789306640625}, "domain": "pixel"}, {"position": {"minX": 149.5, "minY": 252.75, "maxX": 589.5, "maxY": 673.0}, "class_id": 8, "box_caption": "8 0.008", "scores": {"class_score": 0.0082550048828125}, "domain": "pixel"}, {"position": {"minX": 125.125, "minY": 189.375, "maxX": 610.0, "maxY": 675.0}, "class_id": 42, "box_caption": "h 0.008", "scores": {"class_score": 0.00824737548828125}, "domain": "pixel"}, {"position": {"minX": 364.5, "minY": 439.25, "maxX": 575.5, "maxY": 671.5}, "class_id": 41, "box_caption": "g 0.008", "scores": {"class_score": 0.00823211669921875}, "domain": "pixel"}, {"position": {"minX": 2.4375, "minY": -8.875, "maxX": 217.75, "maxY": 367.5}, "class_id": 44, "box_caption": "q 0.008", "scores": {"class_score": 0.00821685791015625}, "domain": "pixel"}, {"position": {"minX": 149.5, "minY": 252.75, "maxX": 589.5, "maxY": 673.0}, "class_id": 0, "box_caption": "0 0.008", "scores": {"class_score": 0.00821685791015625}, "domain": "pixel"}, {"position": {"minX": 130.5, "minY": 253.125, "maxX": 606.0, "maxY": 671.0}, "class_id": 18, "box_caption": "I 0.008", "scores": {"class_score": 0.0081939697265625}, "domain": "pixel"}, {"position": {"minX": 130.5, "minY": 253.125, "maxX": 606.0, "maxY": 671.0}, "class_id": 29, "box_caption": "T 0.008", "scores": {"class_score": 0.0081939697265625}, "domain": "pixel"}, {"position": {"minX": 12.75, "minY": 40.375, "maxX": 345.75, "maxY": 506.0}, "class_id": 2, "box_caption": "2 0.008", "scores": {"class_score": 0.00818634033203125}, "domain": "pixel"}, {"position": {"minX": 12.75, "minY": 40.375, "maxX": 345.75, "maxY": 506.0}, "class_id": 21, "box_caption": "L 0.008", "scores": {"class_score": 0.00817108154296875}, "domain": "pixel"}, {"position": {"minX": 371.5, "minY": 442.0, "maxX": 568.5, "maxY": 671.0}, "class_id": 38, "box_caption": "d 0.008", "scores": {"class_score": 0.00815582275390625}, "domain": "pixel"}, {"position": {"minX": 12.75, "minY": 40.375, "maxX": 345.75, "maxY": 506.0}, "class_id": 29, "box_caption": "T 0.008", "scores": {"class_score": 0.00815582275390625}, "domain": "pixel"}, {"position": {"minX": 368.75, "minY": 444.0, "maxX": 570.5, "maxY": 670.0}, "class_id": 9, "box_caption": "9 0.008", "scores": {"class_score": 0.008148193359375}, "domain": "pixel"}, {"position": {"minX": 12.75, "minY": 40.375, "maxX": 345.75, "maxY": 506.0}, "class_id": 37, "box_caption": "b 0.008", "scores": {"class_score": 0.00814056396484375}, "domain": "pixel"}, {"position": {"minX": 96.25, "minY": 104.5, "maxX": 569.0, "maxY": 633.0}, "class_id": 38, "box_caption": "d 0.008", "scores": {"class_score": 0.00812530517578125}, "domain": "pixel"}, {"position": {"minX": 136.5, "minY": 188.375, "maxX": 600.5, "maxY": 680.0}, "class_id": 13, "box_caption": "D 0.008", "scores": {"class_score": 0.00812530517578125}, "domain": "pixel"}, {"position": {"minX": 125.125, "minY": 189.375, "maxX": 610.0, "maxY": 675.0}, "class_id": 4, "box_caption": "4 0.008", "scores": {"class_score": 0.00811767578125}, "domain": "pixel"}, {"position": {"minX": 136.5, "minY": 188.375, "maxX": 600.5, "maxY": 680.0}, "class_id": 12, "box_caption": "C 0.008", "scores": {"class_score": 0.00809478759765625}, "domain": "pixel"}, {"position": {"minX": 368.75, "minY": 444.0, "maxX": 570.5, "maxY": 670.0}, "class_id": 10, "box_caption": "A 0.008", "scores": {"class_score": 0.00807952880859375}, "domain": "pixel"}, {"position": {"minX": 364.5, "minY": 439.25, "maxX": 575.5, "maxY": 671.5}, "class_id": 4, "box_caption": "4 0.008", "scores": {"class_score": 0.00807952880859375}, "domain": "pixel"}, {"position": {"minX": 371.5, "minY": 442.0, "maxX": 568.5, "maxY": 671.0}, "class_id": 42, "box_caption": "h 0.008", "scores": {"class_score": 0.00804901123046875}, "domain": "pixel"}, {"position": {"minX": 33.5, "minY": 106.0, "maxX": 454.5, "maxY": 626.5}, "class_id": 33, "box_caption": "X 0.008", "scores": {"class_score": 0.00804901123046875}, "domain": "pixel"}, {"position": {"minX": 12.75, "minY": 40.375, "maxX": 345.75, "maxY": 506.0}, "class_id": 44, "box_caption": "q 0.008", "scores": {"class_score": 0.0080413818359375}, "domain": "pixel"}, {"position": {"minX": 364.5, "minY": 439.25, "maxX": 575.5, "maxY": 671.5}, "class_id": 29, "box_caption": "T 0.008", "scores": {"class_score": 0.00803375244140625}, "domain": "pixel"}, {"position": {"minX": 27.25, "minY": 105.5, "maxX": 457.25, "maxY": 626.0}, "class_id": 41, "box_caption": "g 0.008", "scores": {"class_score": 0.008026123046875}, "domain": "pixel"}, {"position": {"minX": 3.25, "minY": -9.0, "maxX": 216.125, "maxY": 368.0}, "class_id": 1, "box_caption": "1 0.008", "scores": {"class_score": 0.00801849365234375}, "domain": "pixel"}, {"position": {"minX": 368.75, "minY": 444.0, "maxX": 570.5, "maxY": 670.0}, "class_id": 15, "box_caption": "F 0.008", "scores": {"class_score": 0.00797271728515625}, "domain": "pixel"}, {"position": {"minX": 32.125, "minY": 104.0, "maxX": 195.625, "maxY": 365.5}, "class_id": 11, "box_caption": "B 0.008", "scores": {"class_score": 0.007965087890625}, "domain": "pixel"}, {"position": {"minX": 244.375, "minY": 274.75, "maxX": 685.5, "maxY": 668.0}, "class_id": 10, "box_caption": "A 0.008", "scores": {"class_score": 0.007904052734375}, "domain": "pixel"}, {"position": {"minX": 244.375, "minY": 274.75, "maxX": 685.5, "maxY": 668.0}, "class_id": 3, "box_caption": "3 0.008", "scores": {"class_score": 0.00785064697265625}, "domain": "pixel"}, {"position": {"minX": 34.375, "minY": 110.625, "maxX": 191.625, "maxY": 360.0}, "class_id": 38, "box_caption": "d 0.008", "scores": {"class_score": 0.007843017578125}, "domain": "pixel"}, {"position": {"minX": 27.25, "minY": 105.5, "maxX": 457.25, "maxY": 626.0}, "class_id": 29, "box_caption": "T 0.008", "scores": {"class_score": 0.007843017578125}, "domain": "pixel"}, {"position": {"minX": 27.25, "minY": 105.5, "maxX": 457.25, "maxY": 626.0}, "class_id": 28, "box_caption": "S 0.008", "scores": {"class_score": 0.0078125}, "domain": "pixel"}, {"position": {"minX": 30.1875, "minY": 103.0, "maxX": 195.75, "maxY": 367.25}, "class_id": 15, "box_caption": "F 0.008", "scores": {"class_score": 0.007770538330078125}, "domain": "pixel"}, {"position": {"minX": 368.75, "minY": 444.0, "maxX": 570.5, "maxY": 670.0}, "class_id": 5, "box_caption": "5 0.008", "scores": {"class_score": 0.0077667236328125}, "domain": "pixel"}, {"position": {"minX": 34.375, "minY": 110.625, "maxX": 191.625, "maxY": 360.0}, "class_id": 6, "box_caption": "6 0.008", "scores": {"class_score": 0.007755279541015625}, "domain": "pixel"}, {"position": {"minX": 34.375, "minY": 110.625, "maxX": 191.625, "maxY": 360.0}, "class_id": 12, "box_caption": "C 0.008", "scores": {"class_score": 0.007755279541015625}, "domain": "pixel"}, {"position": {"minX": 27.25, "minY": 105.5, "maxX": 457.25, "maxY": 626.0}, "class_id": 9, "box_caption": "9 0.008", "scores": {"class_score": 0.007740020751953125}, "domain": "pixel"}, {"position": {"minX": 96.25, "minY": 104.5, "maxX": 569.0, "maxY": 633.0}, "class_id": 35, "box_caption": "Z 0.008", "scores": {"class_score": 0.00772857666015625}, "domain": "pixel"}, {"position": {"minX": 364.5, "minY": 439.25, "maxX": 575.5, "maxY": 671.5}, "class_id": 3, "box_caption": "3 0.008", "scores": {"class_score": 0.007720947265625}, "domain": "pixel"}, {"position": {"minX": 33.5, "minY": 106.0, "maxX": 454.5, "maxY": 626.5}, "class_id": 43, "box_caption": "n 0.008", "scores": {"class_score": 0.007717132568359375}, "domain": "pixel"}, {"position": {"minX": 27.25, "minY": 105.5, "maxX": 457.25, "maxY": 626.0}, "class_id": 46, "box_caption": "t 0.008", "scores": {"class_score": 0.00771331787109375}, "domain": "pixel"}, {"position": {"minX": 34.375, "minY": 110.625, "maxX": 191.625, "maxY": 360.0}, "class_id": 37, "box_caption": "b 0.008", "scores": {"class_score": 0.007709503173828125}, "domain": "pixel"}, {"position": {"minX": 27.25, "minY": 105.5, "maxX": 457.25, "maxY": 626.0}, "class_id": 26, "box_caption": "Q 0.008", "scores": {"class_score": 0.00766754150390625}, "domain": "pixel"}, {"position": {"minX": 27.25, "minY": 105.5, "maxX": 457.25, "maxY": 626.0}, "class_id": 13, "box_caption": "D 0.008", "scores": {"class_score": 0.00763702392578125}, "domain": "pixel"}, {"position": {"minX": 364.5, "minY": 439.25, "maxX": 575.5, "maxY": 671.5}, "class_id": 40, "box_caption": "f 0.008", "scores": {"class_score": 0.007633209228515625}, "domain": "pixel"}, {"position": {"minX": 33.5, "minY": 106.0, "maxX": 454.5, "maxY": 626.5}, "class_id": 14, "box_caption": "E 0.008", "scores": {"class_score": 0.0076141357421875}, "domain": "pixel"}, {"position": {"minX": 368.75, "minY": 444.0, "maxX": 570.5, "maxY": 670.0}, "class_id": 37, "box_caption": "b 0.008", "scores": {"class_score": 0.007549285888671875}, "domain": "pixel"}, {"position": {"minX": 30.1875, "minY": 103.0, "maxX": 195.75, "maxY": 367.25}, "class_id": 33, "box_caption": "X 0.008", "scores": {"class_score": 0.007549285888671875}, "domain": "pixel"}, {"position": {"minX": 364.5, "minY": 439.25, "maxX": 575.5, "maxY": 671.5}, "class_id": 20, "box_caption": "K 0.008", "scores": {"class_score": 0.007541656494140625}, "domain": "pixel"}, {"position": {"minX": 34.375, "minY": 110.625, "maxX": 191.625, "maxY": 360.0}, "class_id": 4, "box_caption": "4 0.008", "scores": {"class_score": 0.007537841796875}, "domain": "pixel"}, {"position": {"minX": 371.5, "minY": 442.0, "maxX": 568.5, "maxY": 671.0}, "class_id": 8, "box_caption": "8 0.008", "scores": {"class_score": 0.00751495361328125}, "domain": "pixel"}, {"position": {"minX": 33.5, "minY": 106.0, "maxX": 454.5, "maxY": 626.5}, "class_id": 7, "box_caption": "7 0.008", "scores": {"class_score": 0.00751495361328125}, "domain": "pixel"}, {"position": {"minX": 34.375, "minY": 110.625, "maxX": 191.625, "maxY": 360.0}, "class_id": 41, "box_caption": "g 0.007", "scores": {"class_score": 0.007495880126953125}, "domain": "pixel"}, {"position": {"minX": 27.25, "minY": 105.5, "maxX": 457.25, "maxY": 626.0}, "class_id": 39, "box_caption": "e 0.007", "scores": {"class_score": 0.0074920654296875}, "domain": "pixel"}, {"position": {"minX": 368.75, "minY": 444.0, "maxX": 570.5, "maxY": 670.0}, "class_id": 22, "box_caption": "M 0.007", "scores": {"class_score": 0.007488250732421875}, "domain": "pixel"}, {"position": {"minX": 27.25, "minY": 105.5, "maxX": 457.25, "maxY": 626.0}, "class_id": 20, "box_caption": "K 0.007", "scores": {"class_score": 0.007476806640625}, "domain": "pixel"}, {"position": {"minX": 30.1875, "minY": 103.0, "maxX": 195.75, "maxY": 367.25}, "class_id": 25, "box_caption": "P 0.007", "scores": {"class_score": 0.007476806640625}, "domain": "pixel"}, {"position": {"minX": 371.5, "minY": 442.0, "maxX": 568.5, "maxY": 671.0}, "class_id": 17, "box_caption": "H 0.007", "scores": {"class_score": 0.007457733154296875}, "domain": "pixel"}, {"position": {"minX": 34.375, "minY": 110.625, "maxX": 191.625, "maxY": 360.0}, "class_id": 16, "box_caption": "G 0.007", "scores": {"class_score": 0.0074462890625}, "domain": "pixel"}, {"position": {"minX": 27.25, "minY": 105.5, "maxX": 457.25, "maxY": 626.0}, "class_id": 45, "box_caption": "r 0.007", "scores": {"class_score": 0.007434844970703125}, "domain": "pixel"}, {"position": {"minX": 34.375, "minY": 110.625, "maxX": 191.625, "maxY": 360.0}, "class_id": 14, "box_caption": "E 0.007", "scores": {"class_score": 0.007404327392578125}, "domain": "pixel"}, {"position": {"minX": 34.375, "minY": 110.625, "maxX": 191.625, "maxY": 360.0}, "class_id": 28, "box_caption": "S 0.007", "scores": {"class_score": 0.007404327392578125}, "domain": "pixel"}, {"position": {"minX": 34.375, "minY": 110.625, "maxX": 191.625, "maxY": 360.0}, "class_id": 5, "box_caption": "5 0.007", "scores": {"class_score": 0.007396697998046875}, "domain": "pixel"}, {"position": {"minX": 225.0, "minY": 324.5, "maxX": 634.0, "maxY": 670.5}, "class_id": 4, "box_caption": "4 0.007", "scores": {"class_score": 0.00739288330078125}, "domain": "pixel"}, {"position": {"minX": 34.375, "minY": 110.625, "maxX": 191.625, "maxY": 360.0}, "class_id": 19, "box_caption": "J 0.007", "scores": {"class_score": 0.007381439208984375}, "domain": "pixel"}, {"position": {"minX": 27.25, "minY": 105.5, "maxX": 457.25, "maxY": 626.0}, "class_id": 3, "box_caption": "3 0.007", "scores": {"class_score": 0.007366180419921875}, "domain": "pixel"}, {"position": {"minX": 371.5, "minY": 442.0, "maxX": 568.5, "maxY": 671.0}, "class_id": 33, "box_caption": "X 0.007", "scores": {"class_score": 0.007343292236328125}, "domain": "pixel"}, {"position": {"minX": 33.5, "minY": 106.0, "maxX": 454.5, "maxY": 626.5}, "class_id": 34, "box_caption": "Y 0.007", "scores": {"class_score": 0.007343292236328125}, "domain": "pixel"}, {"position": {"minX": 249.5, "minY": 274.0, "maxX": 677.5, "maxY": 666.5}, "class_id": 33, "box_caption": "X 0.007", "scores": {"class_score": 0.007328033447265625}, "domain": "pixel"}, {"position": {"minX": 34.375, "minY": 110.625, "maxX": 191.625, "maxY": 360.0}, "class_id": 9, "box_caption": "9 0.007", "scores": {"class_score": 0.007305145263671875}, "domain": "pixel"}, {"position": {"minX": 34.375, "minY": 110.625, "maxX": 191.625, "maxY": 360.0}, "class_id": 24, "box_caption": "O 0.007", "scores": {"class_score": 0.007305145263671875}, "domain": "pixel"}, {"position": {"minX": 34.375, "minY": 110.625, "maxX": 191.625, "maxY": 360.0}, "class_id": 3, "box_caption": "3 0.007", "scores": {"class_score": 0.007297515869140625}, "domain": "pixel"}, {"position": {"minX": 34.375, "minY": 110.625, "maxX": 191.625, "maxY": 360.0}, "class_id": 35, "box_caption": "Z 0.007", "scores": {"class_score": 0.007297515869140625}, "domain": "pixel"}, {"position": {"minX": 32.125, "minY": 104.0, "maxX": 195.625, "maxY": 365.5}, "class_id": 27, "box_caption": "R 0.007", "scores": {"class_score": 0.007297515869140625}, "domain": "pixel"}, {"position": {"minX": 27.25, "minY": 105.5, "maxX": 457.25, "maxY": 626.0}, "class_id": 24, "box_caption": "O 0.007", "scores": {"class_score": 0.007282257080078125}, "domain": "pixel"}, {"position": {"minX": 27.25, "minY": 105.5, "maxX": 457.25, "maxY": 626.0}, "class_id": 42, "box_caption": "h 0.007", "scores": {"class_score": 0.007282257080078125}, "domain": "pixel"}, {"position": {"minX": 368.75, "minY": 444.0, "maxX": 570.5, "maxY": 670.0}, "class_id": 21, "box_caption": "L 0.007", "scores": {"class_score": 0.007251739501953125}, "domain": "pixel"}, {"position": {"minX": 107.375, "minY": 102.5, "maxX": 557.5, "maxY": 635.0}, "class_id": 17, "box_caption": "H 0.007", "scores": {"class_score": 0.007244110107421875}, "domain": "pixel"}, {"position": {"minX": 34.375, "minY": 110.625, "maxX": 191.625, "maxY": 360.0}, "class_id": 23, "box_caption": "N 0.007", "scores": {"class_score": 0.00724029541015625}, "domain": "pixel"}, {"position": {"minX": 228.625, "minY": 326.5, "maxX": 630.5, "maxY": 668.5}, "class_id": 15, "box_caption": "F 0.007", "scores": {"class_score": 0.007236480712890625}, "domain": "pixel"}, {"position": {"minX": 34.375, "minY": 110.625, "maxX": 191.625, "maxY": 360.0}, "class_id": 7, "box_caption": "7 0.007", "scores": {"class_score": 0.00722503662109375}, "domain": "pixel"}, {"position": {"minX": 32.125, "minY": 104.0, "maxX": 195.625, "maxY": 365.5}, "class_id": 39, "box_caption": "e 0.007", "scores": {"class_score": 0.0072021484375}, "domain": "pixel"}, {"position": {"minX": 34.375, "minY": 110.625, "maxX": 191.625, "maxY": 360.0}, "class_id": 40, "box_caption": "f 0.007", "scores": {"class_score": 0.007198333740234375}, "domain": "pixel"}, {"position": {"minX": 34.375, "minY": 110.625, "maxX": 191.625, "maxY": 360.0}, "class_id": 22, "box_caption": "M 0.007", "scores": {"class_score": 0.0071868896484375}, "domain": "pixel"}, {"position": {"minX": 136.75, "minY": 151.875, "maxX": 460.25, "maxY": 584.5}, "class_id": 5, "box_caption": "5 0.007", "scores": {"class_score": 0.007171630859375}, "domain": "pixel"}, {"position": {"minX": 244.375, "minY": 274.75, "maxX": 685.5, "maxY": 668.0}, "class_id": 42, "box_caption": "h 0.007", "scores": {"class_score": 0.007167816162109375}, "domain": "pixel"}, {"position": {"minX": 30.1875, "minY": 103.0, "maxX": 195.75, "maxY": 367.25}, "class_id": 36, "box_caption": "a 0.007", "scores": {"class_score": 0.0071563720703125}, "domain": "pixel"}, {"position": {"minX": 27.25, "minY": 105.5, "maxX": 457.25, "maxY": 626.0}, "class_id": 0, "box_caption": "0 0.007", "scores": {"class_score": 0.007144927978515625}, "domain": "pixel"}, {"position": {"minX": 34.375, "minY": 110.625, "maxX": 191.625, "maxY": 360.0}, "class_id": 30, "box_caption": "U 0.007", "scores": {"class_score": 0.007129669189453125}, "domain": "pixel"}, {"position": {"minX": 244.375, "minY": 274.75, "maxX": 685.5, "maxY": 668.0}, "class_id": 9, "box_caption": "9 0.007", "scores": {"class_score": 0.0071258544921875}, "domain": "pixel"}, {"position": {"minX": 371.5, "minY": 442.0, "maxX": 568.5, "maxY": 671.0}, "class_id": 43, "box_caption": "n 0.007", "scores": {"class_score": 0.0071258544921875}, "domain": "pixel"}, {"position": {"minX": 34.375, "minY": 110.625, "maxX": 191.625, "maxY": 360.0}, "class_id": 2, "box_caption": "2 0.007", "scores": {"class_score": 0.007114410400390625}, "domain": "pixel"}, {"position": {"minX": 96.25, "minY": 104.5, "maxX": 569.0, "maxY": 633.0}, "class_id": 44, "box_caption": "q 0.007", "scores": {"class_score": 0.007091522216796875}, "domain": "pixel"}], "class_labels": {"0": "0", "1": "1", "2": "2", "3": "3", "4": "4", "5": "5", "6": "6", "7": "7", "8": "8", "9": "9", "10": "A", "11": "B", "12": "C", "13": "D", "14": "E", "15": "F", "16": "G", "17": "H", "18": "I", "19": "J", "20": "K", "21": "L", "22": "M", "23": "N", "24": "O", "25": "P", "26": "Q", "27": "R", "28": "S", "29": "T", "30": "U", "31": "V", "32": "W", "33": "X", "34": "Y", "35": "Z", "36": "a", "37": "b", "38": "d", "39": "e", "40": "f", "41": "g", "42": "h", "43": "n", "44": "q", "45": "r", "46": "t"}}